{
  "generated_at": "2026-06-06T02:00:12.581Z",
  "model": "10-account (5 strategies x 2 exit rules)",
  "totals": {
    "equity": 100072.66,
    "starting": 100000,
    "pnl_dollars": 72.66,
    "pnl_pct": 0.07,
    "open_positions": 21,
    "book_count": 10
  },
  "strategies": [
    "news_only",
    "news_plus_ta",
    "mean_reversion",
    "trend_strict",
    "strict"
  ],
  "exit_rules": [
    "hold_24hr",
    "sell_eod"
  ],
  "books": [
    {
      "portfolio": "mean_reversion",
      "exit_rule": "hold_24hr",
      "book_key": "mean_reversion__hold_24hr",
      "starting_balance": 10000,
      "total_equity": 10000,
      "growth_dollars": 0,
      "growth_pct": 0,
      "free_cash": 10000,
      "deployed_capital": 0,
      "cash_pct": 100,
      "invested_pct": 0,
      "open_count": 0,
      "analytics": {
        "OVERALL": {
          "total_closed": 1,
          "wins": 0,
          "losses": 1,
          "win_rate_pct": 0,
          "avg_win_pct": 0,
          "avg_loss_pct": 0,
          "reward_risk_ratio": 0,
          "total_pnl_pct": 0,
          "total_pnl_dollars": 0
        },
        "BY_ASSET": [
          {
            "key": "DRVN",
            "count": 1,
            "win_rate_pct": 0,
            "total_pnl_pct": 0,
            "total_pnl_dollars": 0
          }
        ],
        "BY_SOURCE": [
          {
            "key": "Seeking Alpha RSS",
            "count": 1,
            "win_rate_pct": 0,
            "avg_pnl_pct": 0
          }
        ],
        "BY_CONFIDENCE": [
          {
            "key": "0.60-0.69",
            "count": 1,
            "win_rate_pct": 0
          }
        ],
        "BY_EXIT_REASON": [
          {
            "key": "voided_pre_gate_bug",
            "count": 1,
            "win_rate_pct": 0
          }
        ],
        "BY_DIRECTION": [
          {
            "key": "SELL",
            "count": 1,
            "win_rate_pct": 0,
            "avg_win_pct": 0,
            "avg_loss_pct": 0
          }
        ],
        "BY_ALIGNMENT": [
          {
            "key": "aligned",
            "count": 1,
            "win_rate_pct": 0
          }
        ],
        "BY_RSI_BAND": [
          {
            "key": "neutral (30-70)",
            "count": 1,
            "win_rate_pct": 0
          }
        ],
        "BY_TREND": [
          {
            "key": "below_ma20 (downtrend)",
            "count": 1,
            "win_rate_pct": 0
          }
        ],
        "BY_HOUR": [
          {
            "key": "15:00 MT",
            "count": 1,
            "win_rate_pct": 0
          }
        ],
        "AVG_HOLD_TIME": {
          "avg_minutes": 230.22,
          "avg_win_minutes": null,
          "avg_loss_minutes": null,
          "n": 1
        }
      },
      "closed": {
        "count": 1,
        "wins": 0,
        "losses": 0,
        "win_rate_pct": 0,
        "total_pnl_dollars": 0,
        "low_sample": true
      }
    },
    {
      "portfolio": "mean_reversion",
      "exit_rule": "sell_eod",
      "book_key": "mean_reversion__sell_eod",
      "starting_balance": 10000,
      "total_equity": 10000,
      "growth_dollars": 0,
      "growth_pct": 0,
      "free_cash": 10000,
      "deployed_capital": 0,
      "cash_pct": 100,
      "invested_pct": 0,
      "open_count": 0,
      "analytics": {
        "OVERALL": {
          "total_closed": 1,
          "wins": 0,
          "losses": 1,
          "win_rate_pct": 0,
          "avg_win_pct": 0,
          "avg_loss_pct": 0,
          "reward_risk_ratio": 0,
          "total_pnl_pct": 0,
          "total_pnl_dollars": 0
        },
        "BY_ASSET": [
          {
            "key": "DRVN",
            "count": 1,
            "win_rate_pct": 0,
            "total_pnl_pct": 0,
            "total_pnl_dollars": 0
          }
        ],
        "BY_SOURCE": [
          {
            "key": "Seeking Alpha RSS",
            "count": 1,
            "win_rate_pct": 0,
            "avg_pnl_pct": 0
          }
        ],
        "BY_CONFIDENCE": [
          {
            "key": "0.60-0.69",
            "count": 1,
            "win_rate_pct": 0
          }
        ],
        "BY_EXIT_REASON": [
          {
            "key": "voided_pre_gate_bug",
            "count": 1,
            "win_rate_pct": 0
          }
        ],
        "BY_DIRECTION": [
          {
            "key": "SELL",
            "count": 1,
            "win_rate_pct": 0,
            "avg_win_pct": 0,
            "avg_loss_pct": 0
          }
        ],
        "BY_ALIGNMENT": [
          {
            "key": "aligned",
            "count": 1,
            "win_rate_pct": 0
          }
        ],
        "BY_RSI_BAND": [
          {
            "key": "neutral (30-70)",
            "count": 1,
            "win_rate_pct": 0
          }
        ],
        "BY_TREND": [
          {
            "key": "below_ma20 (downtrend)",
            "count": 1,
            "win_rate_pct": 0
          }
        ],
        "BY_HOUR": [
          {
            "key": "15:00 MT",
            "count": 1,
            "win_rate_pct": 0
          }
        ],
        "AVG_HOLD_TIME": {
          "avg_minutes": 230.22,
          "avg_win_minutes": null,
          "avg_loss_minutes": null,
          "n": 1
        }
      },
      "closed": {
        "count": 1,
        "wins": 0,
        "losses": 0,
        "win_rate_pct": 0,
        "total_pnl_dollars": 0,
        "low_sample": true
      }
    },
    {
      "portfolio": "news_only",
      "exit_rule": "hold_24hr",
      "book_key": "news_only__hold_24hr",
      "starting_balance": 10000,
      "total_equity": 10017.68,
      "growth_dollars": 17.68,
      "growth_pct": 0.18,
      "free_cash": 5314.41,
      "deployed_capital": 4703.27,
      "cash_pct": 53.05,
      "invested_pct": 46.95,
      "open_count": 6,
      "analytics": {
        "OVERALL": {
          "total_closed": 8,
          "wins": 0,
          "losses": 8,
          "win_rate_pct": 0,
          "avg_win_pct": 0,
          "avg_loss_pct": 0,
          "reward_risk_ratio": 0,
          "total_pnl_pct": 0,
          "total_pnl_dollars": 0
        },
        "BY_ASSET": [
          {
            "key": "COIN",
            "count": 1,
            "win_rate_pct": 0,
            "total_pnl_pct": 0,
            "total_pnl_dollars": 0
          },
          {
            "key": "DRVN",
            "count": 1,
            "win_rate_pct": 0,
            "total_pnl_pct": 0,
            "total_pnl_dollars": 0
          },
          {
            "key": "FCPT",
            "count": 1,
            "win_rate_pct": 0,
            "total_pnl_pct": 0,
            "total_pnl_dollars": 0
          },
          {
            "key": "IMNN",
            "count": 1,
            "win_rate_pct": 0,
            "total_pnl_pct": 0,
            "total_pnl_dollars": 0
          },
          {
            "key": "MOBX",
            "count": 1,
            "win_rate_pct": 0,
            "total_pnl_pct": 0,
            "total_pnl_dollars": 0
          },
          {
            "key": "MYND",
            "count": 1,
            "win_rate_pct": 0,
            "total_pnl_pct": 0,
            "total_pnl_dollars": 0
          },
          {
            "key": "PVH",
            "count": 1,
            "win_rate_pct": 0,
            "total_pnl_pct": 0,
            "total_pnl_dollars": 0
          },
          {
            "key": "RUM",
            "count": 1,
            "win_rate_pct": 0,
            "total_pnl_pct": 0,
            "total_pnl_dollars": 0
          }
        ],
        "BY_SOURCE": [
          {
            "key": "Business Wire RSS",
            "count": 1,
            "win_rate_pct": 0,
            "avg_pnl_pct": 0
          },
          {
            "key": "Seeking Alpha RSS",
            "count": 2,
            "win_rate_pct": 0,
            "avg_pnl_pct": 0
          },
          {
            "key": "Yahoo Finance RSS",
            "count": 5,
            "win_rate_pct": 0,
            "avg_pnl_pct": 0
          }
        ],
        "BY_CONFIDENCE": [
          {
            "key": "0.60-0.69",
            "count": 3,
            "win_rate_pct": 0
          },
          {
            "key": "0.70-0.79",
            "count": 5,
            "win_rate_pct": 0
          }
        ],
        "BY_EXIT_REASON": [
          {
            "key": "voided_pre_gate_bug",
            "count": 8,
            "win_rate_pct": 0
          }
        ],
        "BY_DIRECTION": [
          {
            "key": "BUY",
            "count": 5,
            "win_rate_pct": 0,
            "avg_win_pct": 0,
            "avg_loss_pct": 0
          },
          {
            "key": "SELL",
            "count": 3,
            "win_rate_pct": 0,
            "avg_win_pct": 0,
            "avg_loss_pct": 0
          }
        ],
        "BY_ALIGNMENT": [
          {
            "key": "aligned",
            "count": 2,
            "win_rate_pct": 0
          },
          {
            "key": "conflict",
            "count": 5,
            "win_rate_pct": 0
          },
          {
            "key": "neutral",
            "count": 1,
            "win_rate_pct": 0
          }
        ],
        "BY_RSI_BAND": [
          {
            "key": "neutral (30-70)",
            "count": 6,
            "win_rate_pct": 0
          },
          {
            "key": "oversold (<30)",
            "count": 2,
            "win_rate_pct": 0
          }
        ],
        "BY_TREND": [
          {
            "key": "above_ma20 (uptrend)",
            "count": 1,
            "win_rate_pct": 0
          },
          {
            "key": "below_ma20 (downtrend)",
            "count": 7,
            "win_rate_pct": 0
          }
        ],
        "BY_HOUR": [
          {
            "key": "14:00 MT",
            "count": 1,
            "win_rate_pct": 0
          },
          {
            "key": "15:00 MT",
            "count": 4,
            "win_rate_pct": 0
          },
          {
            "key": "16:00 MT",
            "count": 3,
            "win_rate_pct": 0
          }
        ],
        "AVG_HOLD_TIME": {
          "avg_minutes": 211.47,
          "avg_win_minutes": null,
          "avg_loss_minutes": null,
          "n": 8
        }
      },
      "closed": {
        "count": 8,
        "wins": 0,
        "losses": 0,
        "win_rate_pct": 0,
        "total_pnl_dollars": 0,
        "low_sample": true
      }
    },
    {
      "portfolio": "news_only",
      "exit_rule": "sell_eod",
      "book_key": "news_only__sell_eod",
      "starting_balance": 10000,
      "total_equity": 10019.59,
      "growth_dollars": 19.59,
      "growth_pct": 0.2,
      "free_cash": 5980.1,
      "deployed_capital": 4039.5,
      "cash_pct": 59.68,
      "invested_pct": 40.32,
      "open_count": 5,
      "analytics": {
        "OVERALL": {
          "total_closed": 9,
          "wins": 1,
          "losses": 8,
          "win_rate_pct": 11.11,
          "avg_win_pct": 1.46,
          "avg_loss_pct": 0,
          "reward_risk_ratio": 0,
          "total_pnl_pct": 1.46,
          "total_pnl_dollars": 9.59
        },
        "BY_ASSET": [
          {
            "key": "COIN",
            "count": 1,
            "win_rate_pct": 0,
            "total_pnl_pct": 0,
            "total_pnl_dollars": 0
          },
          {
            "key": "DRVN",
            "count": 1,
            "win_rate_pct": 0,
            "total_pnl_pct": 0,
            "total_pnl_dollars": 0
          },
          {
            "key": "FCPT",
            "count": 1,
            "win_rate_pct": 0,
            "total_pnl_pct": 0,
            "total_pnl_dollars": 0
          },
          {
            "key": "IMNN",
            "count": 1,
            "win_rate_pct": 0,
            "total_pnl_pct": 0,
            "total_pnl_dollars": 0
          },
          {
            "key": "MIRM",
            "count": 1,
            "win_rate_pct": 100,
            "total_pnl_pct": 1.46,
            "total_pnl_dollars": 9.59
          },
          {
            "key": "MOBX",
            "count": 1,
            "win_rate_pct": 0,
            "total_pnl_pct": 0,
            "total_pnl_dollars": 0
          },
          {
            "key": "MYND",
            "count": 1,
            "win_rate_pct": 0,
            "total_pnl_pct": 0,
            "total_pnl_dollars": 0
          },
          {
            "key": "PVH",
            "count": 1,
            "win_rate_pct": 0,
            "total_pnl_pct": 0,
            "total_pnl_dollars": 0
          },
          {
            "key": "RUM",
            "count": 1,
            "win_rate_pct": 0,
            "total_pnl_pct": 0,
            "total_pnl_dollars": 0
          }
        ],
        "BY_SOURCE": [
          {
            "key": "Business Wire RSS",
            "count": 1,
            "win_rate_pct": 0,
            "avg_pnl_pct": 0
          },
          {
            "key": "Seeking Alpha RSS",
            "count": 2,
            "win_rate_pct": 0,
            "avg_pnl_pct": 0
          },
          {
            "key": "Yahoo Finance RSS",
            "count": 6,
            "win_rate_pct": 16.67,
            "avg_pnl_pct": 0.24
          }
        ],
        "BY_CONFIDENCE": [
          {
            "key": "0.60-0.69",
            "count": 3,
            "win_rate_pct": 0
          },
          {
            "key": "0.70-0.79",
            "count": 6,
            "win_rate_pct": 16.67
          }
        ],
        "BY_EXIT_REASON": [
          {
            "key": "eod",
            "count": 1,
            "win_rate_pct": 100
          },
          {
            "key": "voided_pre_gate_bug",
            "count": 8,
            "win_rate_pct": 0
          }
        ],
        "BY_DIRECTION": [
          {
            "key": "BUY",
            "count": 6,
            "win_rate_pct": 16.67,
            "avg_win_pct": 1.46,
            "avg_loss_pct": 0
          },
          {
            "key": "SELL",
            "count": 3,
            "win_rate_pct": 0,
            "avg_win_pct": 0,
            "avg_loss_pct": 0
          }
        ],
        "BY_ALIGNMENT": [
          {
            "key": "aligned",
            "count": 2,
            "win_rate_pct": 0
          },
          {
            "key": "conflict",
            "count": 6,
            "win_rate_pct": 16.67
          },
          {
            "key": "neutral",
            "count": 1,
            "win_rate_pct": 0
          }
        ],
        "BY_RSI_BAND": [
          {
            "key": "neutral (30-70)",
            "count": 7,
            "win_rate_pct": 14.29
          },
          {
            "key": "oversold (<30)",
            "count": 2,
            "win_rate_pct": 0
          }
        ],
        "BY_TREND": [
          {
            "key": "above_ma20 (uptrend)",
            "count": 1,
            "win_rate_pct": 0
          },
          {
            "key": "below_ma20 (downtrend)",
            "count": 8,
            "win_rate_pct": 12.5
          }
        ],
        "BY_HOUR": [
          {
            "key": "12:00 MT",
            "count": 1,
            "win_rate_pct": 100
          },
          {
            "key": "14:00 MT",
            "count": 1,
            "win_rate_pct": 0
          },
          {
            "key": "15:00 MT",
            "count": 4,
            "win_rate_pct": 0
          },
          {
            "key": "16:00 MT",
            "count": 3,
            "win_rate_pct": 0
          }
        ],
        "AVG_HOLD_TIME": {
          "avg_minutes": 196.18,
          "avg_win_minutes": 73.86,
          "avg_loss_minutes": null,
          "n": 9
        }
      },
      "closed": {
        "count": 9,
        "wins": 1,
        "losses": 0,
        "win_rate_pct": 11.11,
        "total_pnl_dollars": 9.59,
        "low_sample": true
      }
    },
    {
      "portfolio": "news_plus_ta",
      "exit_rule": "hold_24hr",
      "book_key": "news_plus_ta__hold_24hr",
      "starting_balance": 10000,
      "total_equity": 9999.15,
      "growth_dollars": -0.85,
      "growth_pct": -0.01,
      "free_cash": 7290,
      "deployed_capital": 2709.15,
      "cash_pct": 72.91,
      "invested_pct": 27.09,
      "open_count": 3,
      "analytics": {
        "OVERALL": {
          "total_closed": 3,
          "wins": 0,
          "losses": 3,
          "win_rate_pct": 0,
          "avg_win_pct": 0,
          "avg_loss_pct": 0,
          "reward_risk_ratio": 0,
          "total_pnl_pct": 0,
          "total_pnl_dollars": 0
        },
        "BY_ASSET": [
          {
            "key": "DRVN",
            "count": 1,
            "win_rate_pct": 0,
            "total_pnl_pct": 0,
            "total_pnl_dollars": 0
          },
          {
            "key": "MYND",
            "count": 1,
            "win_rate_pct": 0,
            "total_pnl_pct": 0,
            "total_pnl_dollars": 0
          },
          {
            "key": "PVH",
            "count": 1,
            "win_rate_pct": 0,
            "total_pnl_pct": 0,
            "total_pnl_dollars": 0
          }
        ],
        "BY_SOURCE": [
          {
            "key": "Seeking Alpha RSS",
            "count": 2,
            "win_rate_pct": 0,
            "avg_pnl_pct": 0
          },
          {
            "key": "Yahoo Finance RSS",
            "count": 1,
            "win_rate_pct": 0,
            "avg_pnl_pct": 0
          }
        ],
        "BY_CONFIDENCE": [
          {
            "key": "0.60-0.69",
            "count": 1,
            "win_rate_pct": 0
          },
          {
            "key": "0.70-0.79",
            "count": 2,
            "win_rate_pct": 0
          }
        ],
        "BY_EXIT_REASON": [
          {
            "key": "voided_pre_gate_bug",
            "count": 3,
            "win_rate_pct": 0
          }
        ],
        "BY_DIRECTION": [
          {
            "key": "SELL",
            "count": 3,
            "win_rate_pct": 0,
            "avg_win_pct": 0,
            "avg_loss_pct": 0
          }
        ],
        "BY_ALIGNMENT": [
          {
            "key": "aligned",
            "count": 2,
            "win_rate_pct": 0
          },
          {
            "key": "neutral",
            "count": 1,
            "win_rate_pct": 0
          }
        ],
        "BY_RSI_BAND": [
          {
            "key": "neutral (30-70)",
            "count": 3,
            "win_rate_pct": 0
          }
        ],
        "BY_TREND": [
          {
            "key": "above_ma20 (uptrend)",
            "count": 1,
            "win_rate_pct": 0
          },
          {
            "key": "below_ma20 (downtrend)",
            "count": 2,
            "win_rate_pct": 0
          }
        ],
        "BY_HOUR": [
          {
            "key": "14:00 MT",
            "count": 1,
            "win_rate_pct": 0
          },
          {
            "key": "15:00 MT",
            "count": 2,
            "win_rate_pct": 0
          }
        ],
        "AVG_HOLD_TIME": {
          "avg_minutes": 240.19,
          "avg_win_minutes": null,
          "avg_loss_minutes": null,
          "n": 3
        }
      },
      "closed": {
        "count": 3,
        "wins": 0,
        "losses": 0,
        "win_rate_pct": 0,
        "total_pnl_dollars": 0,
        "low_sample": true
      }
    },
    {
      "portfolio": "news_plus_ta",
      "exit_rule": "sell_eod",
      "book_key": "news_plus_ta__sell_eod",
      "starting_balance": 10000,
      "total_equity": 9999.15,
      "growth_dollars": -0.85,
      "growth_pct": -0.01,
      "free_cash": 7290,
      "deployed_capital": 2709.15,
      "cash_pct": 72.91,
      "invested_pct": 27.09,
      "open_count": 3,
      "analytics": {
        "OVERALL": {
          "total_closed": 3,
          "wins": 0,
          "losses": 3,
          "win_rate_pct": 0,
          "avg_win_pct": 0,
          "avg_loss_pct": 0,
          "reward_risk_ratio": 0,
          "total_pnl_pct": 0,
          "total_pnl_dollars": 0
        },
        "BY_ASSET": [
          {
            "key": "DRVN",
            "count": 1,
            "win_rate_pct": 0,
            "total_pnl_pct": 0,
            "total_pnl_dollars": 0
          },
          {
            "key": "MYND",
            "count": 1,
            "win_rate_pct": 0,
            "total_pnl_pct": 0,
            "total_pnl_dollars": 0
          },
          {
            "key": "PVH",
            "count": 1,
            "win_rate_pct": 0,
            "total_pnl_pct": 0,
            "total_pnl_dollars": 0
          }
        ],
        "BY_SOURCE": [
          {
            "key": "Seeking Alpha RSS",
            "count": 2,
            "win_rate_pct": 0,
            "avg_pnl_pct": 0
          },
          {
            "key": "Yahoo Finance RSS",
            "count": 1,
            "win_rate_pct": 0,
            "avg_pnl_pct": 0
          }
        ],
        "BY_CONFIDENCE": [
          {
            "key": "0.60-0.69",
            "count": 1,
            "win_rate_pct": 0
          },
          {
            "key": "0.70-0.79",
            "count": 2,
            "win_rate_pct": 0
          }
        ],
        "BY_EXIT_REASON": [
          {
            "key": "voided_pre_gate_bug",
            "count": 3,
            "win_rate_pct": 0
          }
        ],
        "BY_DIRECTION": [
          {
            "key": "SELL",
            "count": 3,
            "win_rate_pct": 0,
            "avg_win_pct": 0,
            "avg_loss_pct": 0
          }
        ],
        "BY_ALIGNMENT": [
          {
            "key": "aligned",
            "count": 2,
            "win_rate_pct": 0
          },
          {
            "key": "neutral",
            "count": 1,
            "win_rate_pct": 0
          }
        ],
        "BY_RSI_BAND": [
          {
            "key": "neutral (30-70)",
            "count": 3,
            "win_rate_pct": 0
          }
        ],
        "BY_TREND": [
          {
            "key": "above_ma20 (uptrend)",
            "count": 1,
            "win_rate_pct": 0
          },
          {
            "key": "below_ma20 (downtrend)",
            "count": 2,
            "win_rate_pct": 0
          }
        ],
        "BY_HOUR": [
          {
            "key": "14:00 MT",
            "count": 1,
            "win_rate_pct": 0
          },
          {
            "key": "15:00 MT",
            "count": 2,
            "win_rate_pct": 0
          }
        ],
        "AVG_HOLD_TIME": {
          "avg_minutes": 240.19,
          "avg_win_minutes": null,
          "avg_loss_minutes": null,
          "n": 3
        }
      },
      "closed": {
        "count": 3,
        "wins": 0,
        "losses": 0,
        "win_rate_pct": 0,
        "total_pnl_dollars": 0,
        "low_sample": true
      }
    },
    {
      "portfolio": "strict",
      "exit_rule": "hold_24hr",
      "book_key": "strict__hold_24hr",
      "starting_balance": 10000,
      "total_equity": 10000,
      "growth_dollars": 0,
      "growth_pct": 0,
      "free_cash": 10000,
      "deployed_capital": 0,
      "cash_pct": 100,
      "invested_pct": 0,
      "open_count": 0,
      "analytics": {
        "OVERALL": {
          "total_closed": 0,
          "wins": 0,
          "losses": 0,
          "win_rate_pct": 0,
          "avg_win_pct": 0,
          "avg_loss_pct": 0,
          "reward_risk_ratio": 0,
          "total_pnl_pct": 0,
          "total_pnl_dollars": 0
        },
        "BY_ASSET": [],
        "BY_SOURCE": [],
        "BY_CONFIDENCE": [],
        "BY_EXIT_REASON": [],
        "BY_DIRECTION": [],
        "BY_ALIGNMENT": [],
        "BY_RSI_BAND": [],
        "BY_TREND": [],
        "BY_HOUR": [],
        "AVG_HOLD_TIME": {
          "avg_minutes": null,
          "avg_win_minutes": null,
          "avg_loss_minutes": null,
          "n": 0
        }
      },
      "closed": {
        "count": 0,
        "wins": 0,
        "losses": 0,
        "win_rate_pct": null,
        "total_pnl_dollars": 0,
        "low_sample": true
      }
    },
    {
      "portfolio": "strict",
      "exit_rule": "sell_eod",
      "book_key": "strict__sell_eod",
      "starting_balance": 10000,
      "total_equity": 10000,
      "growth_dollars": 0,
      "growth_pct": 0,
      "free_cash": 10000,
      "deployed_capital": 0,
      "cash_pct": 100,
      "invested_pct": 0,
      "open_count": 0,
      "analytics": {
        "OVERALL": {
          "total_closed": 0,
          "wins": 0,
          "losses": 0,
          "win_rate_pct": 0,
          "avg_win_pct": 0,
          "avg_loss_pct": 0,
          "reward_risk_ratio": 0,
          "total_pnl_pct": 0,
          "total_pnl_dollars": 0
        },
        "BY_ASSET": [],
        "BY_SOURCE": [],
        "BY_CONFIDENCE": [],
        "BY_EXIT_REASON": [],
        "BY_DIRECTION": [],
        "BY_ALIGNMENT": [],
        "BY_RSI_BAND": [],
        "BY_TREND": [],
        "BY_HOUR": [],
        "AVG_HOLD_TIME": {
          "avg_minutes": null,
          "avg_win_minutes": null,
          "avg_loss_minutes": null,
          "n": 0
        }
      },
      "closed": {
        "count": 0,
        "wins": 0,
        "losses": 0,
        "win_rate_pct": null,
        "total_pnl_dollars": 0,
        "low_sample": true
      }
    },
    {
      "portfolio": "trend_strict",
      "exit_rule": "hold_24hr",
      "book_key": "trend_strict__hold_24hr",
      "starting_balance": 10000,
      "total_equity": 10018.54,
      "growth_dollars": 18.54,
      "growth_pct": 0.19,
      "free_cash": 8100,
      "deployed_capital": 1918.54,
      "cash_pct": 80.85,
      "invested_pct": 19.15,
      "open_count": 2,
      "analytics": {
        "OVERALL": {
          "total_closed": 2,
          "wins": 0,
          "losses": 2,
          "win_rate_pct": 0,
          "avg_win_pct": 0,
          "avg_loss_pct": 0,
          "reward_risk_ratio": 0,
          "total_pnl_pct": 0,
          "total_pnl_dollars": 0
        },
        "BY_ASSET": [
          {
            "key": "DRVN",
            "count": 1,
            "win_rate_pct": 0,
            "total_pnl_pct": 0,
            "total_pnl_dollars": 0
          },
          {
            "key": "PVH",
            "count": 1,
            "win_rate_pct": 0,
            "total_pnl_pct": 0,
            "total_pnl_dollars": 0
          }
        ],
        "BY_SOURCE": [
          {
            "key": "Seeking Alpha RSS",
            "count": 1,
            "win_rate_pct": 0,
            "avg_pnl_pct": 0
          },
          {
            "key": "Yahoo Finance RSS",
            "count": 1,
            "win_rate_pct": 0,
            "avg_pnl_pct": 0
          }
        ],
        "BY_CONFIDENCE": [
          {
            "key": "0.60-0.69",
            "count": 1,
            "win_rate_pct": 0
          },
          {
            "key": "0.70-0.79",
            "count": 1,
            "win_rate_pct": 0
          }
        ],
        "BY_EXIT_REASON": [
          {
            "key": "voided_pre_gate_bug",
            "count": 2,
            "win_rate_pct": 0
          }
        ],
        "BY_DIRECTION": [
          {
            "key": "SELL",
            "count": 2,
            "win_rate_pct": 0,
            "avg_win_pct": 0,
            "avg_loss_pct": 0
          }
        ],
        "BY_ALIGNMENT": [
          {
            "key": "aligned",
            "count": 2,
            "win_rate_pct": 0
          }
        ],
        "BY_RSI_BAND": [
          {
            "key": "neutral (30-70)",
            "count": 2,
            "win_rate_pct": 0
          }
        ],
        "BY_TREND": [
          {
            "key": "below_ma20 (downtrend)",
            "count": 2,
            "win_rate_pct": 0
          }
        ],
        "BY_HOUR": [
          {
            "key": "14:00 MT",
            "count": 1,
            "win_rate_pct": 0
          },
          {
            "key": "15:00 MT",
            "count": 1,
            "win_rate_pct": 0
          }
        ],
        "AVG_HOLD_TIME": {
          "avg_minutes": 245.18,
          "avg_win_minutes": null,
          "avg_loss_minutes": null,
          "n": 2
        }
      },
      "closed": {
        "count": 2,
        "wins": 0,
        "losses": 0,
        "win_rate_pct": 0,
        "total_pnl_dollars": 0,
        "low_sample": true
      }
    },
    {
      "portfolio": "trend_strict",
      "exit_rule": "sell_eod",
      "book_key": "trend_strict__sell_eod",
      "starting_balance": 10000,
      "total_equity": 10018.54,
      "growth_dollars": 18.54,
      "growth_pct": 0.19,
      "free_cash": 8100,
      "deployed_capital": 1918.54,
      "cash_pct": 80.85,
      "invested_pct": 19.15,
      "open_count": 2,
      "analytics": {
        "OVERALL": {
          "total_closed": 2,
          "wins": 0,
          "losses": 2,
          "win_rate_pct": 0,
          "avg_win_pct": 0,
          "avg_loss_pct": 0,
          "reward_risk_ratio": 0,
          "total_pnl_pct": 0,
          "total_pnl_dollars": 0
        },
        "BY_ASSET": [
          {
            "key": "DRVN",
            "count": 1,
            "win_rate_pct": 0,
            "total_pnl_pct": 0,
            "total_pnl_dollars": 0
          },
          {
            "key": "PVH",
            "count": 1,
            "win_rate_pct": 0,
            "total_pnl_pct": 0,
            "total_pnl_dollars": 0
          }
        ],
        "BY_SOURCE": [
          {
            "key": "Seeking Alpha RSS",
            "count": 1,
            "win_rate_pct": 0,
            "avg_pnl_pct": 0
          },
          {
            "key": "Yahoo Finance RSS",
            "count": 1,
            "win_rate_pct": 0,
            "avg_pnl_pct": 0
          }
        ],
        "BY_CONFIDENCE": [
          {
            "key": "0.60-0.69",
            "count": 1,
            "win_rate_pct": 0
          },
          {
            "key": "0.70-0.79",
            "count": 1,
            "win_rate_pct": 0
          }
        ],
        "BY_EXIT_REASON": [
          {
            "key": "voided_pre_gate_bug",
            "count": 2,
            "win_rate_pct": 0
          }
        ],
        "BY_DIRECTION": [
          {
            "key": "SELL",
            "count": 2,
            "win_rate_pct": 0,
            "avg_win_pct": 0,
            "avg_loss_pct": 0
          }
        ],
        "BY_ALIGNMENT": [
          {
            "key": "aligned",
            "count": 2,
            "win_rate_pct": 0
          }
        ],
        "BY_RSI_BAND": [
          {
            "key": "neutral (30-70)",
            "count": 2,
            "win_rate_pct": 0
          }
        ],
        "BY_TREND": [
          {
            "key": "below_ma20 (downtrend)",
            "count": 2,
            "win_rate_pct": 0
          }
        ],
        "BY_HOUR": [
          {
            "key": "14:00 MT",
            "count": 1,
            "win_rate_pct": 0
          },
          {
            "key": "15:00 MT",
            "count": 1,
            "win_rate_pct": 0
          }
        ],
        "AVG_HOLD_TIME": {
          "avg_minutes": 245.18,
          "avg_win_minutes": null,
          "avg_loss_minutes": null,
          "n": 2
        }
      },
      "closed": {
        "count": 2,
        "wins": 0,
        "losses": 0,
        "win_rate_pct": 0,
        "total_pnl_dollars": 0,
        "low_sample": true
      }
    }
  ],
  "grid": {
    "news_only": {
      "hold_24hr": {
        "portfolio": "news_only",
        "exit_rule": "hold_24hr",
        "book_key": "news_only__hold_24hr",
        "starting_balance": 10000,
        "total_equity": 10017.68,
        "growth_dollars": 17.68,
        "growth_pct": 0.18,
        "free_cash": 5314.41,
        "deployed_capital": 4703.27,
        "cash_pct": 53.05,
        "invested_pct": 46.95,
        "open_count": 6,
        "analytics": {
          "OVERALL": {
            "total_closed": 8,
            "wins": 0,
            "losses": 8,
            "win_rate_pct": 0,
            "avg_win_pct": 0,
            "avg_loss_pct": 0,
            "reward_risk_ratio": 0,
            "total_pnl_pct": 0,
            "total_pnl_dollars": 0
          },
          "BY_ASSET": [
            {
              "key": "COIN",
              "count": 1,
              "win_rate_pct": 0,
              "total_pnl_pct": 0,
              "total_pnl_dollars": 0
            },
            {
              "key": "DRVN",
              "count": 1,
              "win_rate_pct": 0,
              "total_pnl_pct": 0,
              "total_pnl_dollars": 0
            },
            {
              "key": "FCPT",
              "count": 1,
              "win_rate_pct": 0,
              "total_pnl_pct": 0,
              "total_pnl_dollars": 0
            },
            {
              "key": "IMNN",
              "count": 1,
              "win_rate_pct": 0,
              "total_pnl_pct": 0,
              "total_pnl_dollars": 0
            },
            {
              "key": "MOBX",
              "count": 1,
              "win_rate_pct": 0,
              "total_pnl_pct": 0,
              "total_pnl_dollars": 0
            },
            {
              "key": "MYND",
              "count": 1,
              "win_rate_pct": 0,
              "total_pnl_pct": 0,
              "total_pnl_dollars": 0
            },
            {
              "key": "PVH",
              "count": 1,
              "win_rate_pct": 0,
              "total_pnl_pct": 0,
              "total_pnl_dollars": 0
            },
            {
              "key": "RUM",
              "count": 1,
              "win_rate_pct": 0,
              "total_pnl_pct": 0,
              "total_pnl_dollars": 0
            }
          ],
          "BY_SOURCE": [
            {
              "key": "Business Wire RSS",
              "count": 1,
              "win_rate_pct": 0,
              "avg_pnl_pct": 0
            },
            {
              "key": "Seeking Alpha RSS",
              "count": 2,
              "win_rate_pct": 0,
              "avg_pnl_pct": 0
            },
            {
              "key": "Yahoo Finance RSS",
              "count": 5,
              "win_rate_pct": 0,
              "avg_pnl_pct": 0
            }
          ],
          "BY_CONFIDENCE": [
            {
              "key": "0.60-0.69",
              "count": 3,
              "win_rate_pct": 0
            },
            {
              "key": "0.70-0.79",
              "count": 5,
              "win_rate_pct": 0
            }
          ],
          "BY_EXIT_REASON": [
            {
              "key": "voided_pre_gate_bug",
              "count": 8,
              "win_rate_pct": 0
            }
          ],
          "BY_DIRECTION": [
            {
              "key": "BUY",
              "count": 5,
              "win_rate_pct": 0,
              "avg_win_pct": 0,
              "avg_loss_pct": 0
            },
            {
              "key": "SELL",
              "count": 3,
              "win_rate_pct": 0,
              "avg_win_pct": 0,
              "avg_loss_pct": 0
            }
          ],
          "BY_ALIGNMENT": [
            {
              "key": "aligned",
              "count": 2,
              "win_rate_pct": 0
            },
            {
              "key": "conflict",
              "count": 5,
              "win_rate_pct": 0
            },
            {
              "key": "neutral",
              "count": 1,
              "win_rate_pct": 0
            }
          ],
          "BY_RSI_BAND": [
            {
              "key": "neutral (30-70)",
              "count": 6,
              "win_rate_pct": 0
            },
            {
              "key": "oversold (<30)",
              "count": 2,
              "win_rate_pct": 0
            }
          ],
          "BY_TREND": [
            {
              "key": "above_ma20 (uptrend)",
              "count": 1,
              "win_rate_pct": 0
            },
            {
              "key": "below_ma20 (downtrend)",
              "count": 7,
              "win_rate_pct": 0
            }
          ],
          "BY_HOUR": [
            {
              "key": "14:00 MT",
              "count": 1,
              "win_rate_pct": 0
            },
            {
              "key": "15:00 MT",
              "count": 4,
              "win_rate_pct": 0
            },
            {
              "key": "16:00 MT",
              "count": 3,
              "win_rate_pct": 0
            }
          ],
          "AVG_HOLD_TIME": {
            "avg_minutes": 211.47,
            "avg_win_minutes": null,
            "avg_loss_minutes": null,
            "n": 8
          }
        },
        "closed": {
          "count": 8,
          "wins": 0,
          "losses": 0,
          "win_rate_pct": 0,
          "total_pnl_dollars": 0,
          "low_sample": true
        }
      },
      "sell_eod": {
        "portfolio": "news_only",
        "exit_rule": "sell_eod",
        "book_key": "news_only__sell_eod",
        "starting_balance": 10000,
        "total_equity": 10019.59,
        "growth_dollars": 19.59,
        "growth_pct": 0.2,
        "free_cash": 5980.1,
        "deployed_capital": 4039.5,
        "cash_pct": 59.68,
        "invested_pct": 40.32,
        "open_count": 5,
        "analytics": {
          "OVERALL": {
            "total_closed": 9,
            "wins": 1,
            "losses": 8,
            "win_rate_pct": 11.11,
            "avg_win_pct": 1.46,
            "avg_loss_pct": 0,
            "reward_risk_ratio": 0,
            "total_pnl_pct": 1.46,
            "total_pnl_dollars": 9.59
          },
          "BY_ASSET": [
            {
              "key": "COIN",
              "count": 1,
              "win_rate_pct": 0,
              "total_pnl_pct": 0,
              "total_pnl_dollars": 0
            },
            {
              "key": "DRVN",
              "count": 1,
              "win_rate_pct": 0,
              "total_pnl_pct": 0,
              "total_pnl_dollars": 0
            },
            {
              "key": "FCPT",
              "count": 1,
              "win_rate_pct": 0,
              "total_pnl_pct": 0,
              "total_pnl_dollars": 0
            },
            {
              "key": "IMNN",
              "count": 1,
              "win_rate_pct": 0,
              "total_pnl_pct": 0,
              "total_pnl_dollars": 0
            },
            {
              "key": "MIRM",
              "count": 1,
              "win_rate_pct": 100,
              "total_pnl_pct": 1.46,
              "total_pnl_dollars": 9.59
            },
            {
              "key": "MOBX",
              "count": 1,
              "win_rate_pct": 0,
              "total_pnl_pct": 0,
              "total_pnl_dollars": 0
            },
            {
              "key": "MYND",
              "count": 1,
              "win_rate_pct": 0,
              "total_pnl_pct": 0,
              "total_pnl_dollars": 0
            },
            {
              "key": "PVH",
              "count": 1,
              "win_rate_pct": 0,
              "total_pnl_pct": 0,
              "total_pnl_dollars": 0
            },
            {
              "key": "RUM",
              "count": 1,
              "win_rate_pct": 0,
              "total_pnl_pct": 0,
              "total_pnl_dollars": 0
            }
          ],
          "BY_SOURCE": [
            {
              "key": "Business Wire RSS",
              "count": 1,
              "win_rate_pct": 0,
              "avg_pnl_pct": 0
            },
            {
              "key": "Seeking Alpha RSS",
              "count": 2,
              "win_rate_pct": 0,
              "avg_pnl_pct": 0
            },
            {
              "key": "Yahoo Finance RSS",
              "count": 6,
              "win_rate_pct": 16.67,
              "avg_pnl_pct": 0.24
            }
          ],
          "BY_CONFIDENCE": [
            {
              "key": "0.60-0.69",
              "count": 3,
              "win_rate_pct": 0
            },
            {
              "key": "0.70-0.79",
              "count": 6,
              "win_rate_pct": 16.67
            }
          ],
          "BY_EXIT_REASON": [
            {
              "key": "eod",
              "count": 1,
              "win_rate_pct": 100
            },
            {
              "key": "voided_pre_gate_bug",
              "count": 8,
              "win_rate_pct": 0
            }
          ],
          "BY_DIRECTION": [
            {
              "key": "BUY",
              "count": 6,
              "win_rate_pct": 16.67,
              "avg_win_pct": 1.46,
              "avg_loss_pct": 0
            },
            {
              "key": "SELL",
              "count": 3,
              "win_rate_pct": 0,
              "avg_win_pct": 0,
              "avg_loss_pct": 0
            }
          ],
          "BY_ALIGNMENT": [
            {
              "key": "aligned",
              "count": 2,
              "win_rate_pct": 0
            },
            {
              "key": "conflict",
              "count": 6,
              "win_rate_pct": 16.67
            },
            {
              "key": "neutral",
              "count": 1,
              "win_rate_pct": 0
            }
          ],
          "BY_RSI_BAND": [
            {
              "key": "neutral (30-70)",
              "count": 7,
              "win_rate_pct": 14.29
            },
            {
              "key": "oversold (<30)",
              "count": 2,
              "win_rate_pct": 0
            }
          ],
          "BY_TREND": [
            {
              "key": "above_ma20 (uptrend)",
              "count": 1,
              "win_rate_pct": 0
            },
            {
              "key": "below_ma20 (downtrend)",
              "count": 8,
              "win_rate_pct": 12.5
            }
          ],
          "BY_HOUR": [
            {
              "key": "12:00 MT",
              "count": 1,
              "win_rate_pct": 100
            },
            {
              "key": "14:00 MT",
              "count": 1,
              "win_rate_pct": 0
            },
            {
              "key": "15:00 MT",
              "count": 4,
              "win_rate_pct": 0
            },
            {
              "key": "16:00 MT",
              "count": 3,
              "win_rate_pct": 0
            }
          ],
          "AVG_HOLD_TIME": {
            "avg_minutes": 196.18,
            "avg_win_minutes": 73.86,
            "avg_loss_minutes": null,
            "n": 9
          }
        },
        "closed": {
          "count": 9,
          "wins": 1,
          "losses": 0,
          "win_rate_pct": 11.11,
          "total_pnl_dollars": 9.59,
          "low_sample": true
        }
      }
    },
    "news_plus_ta": {
      "hold_24hr": {
        "portfolio": "news_plus_ta",
        "exit_rule": "hold_24hr",
        "book_key": "news_plus_ta__hold_24hr",
        "starting_balance": 10000,
        "total_equity": 9999.15,
        "growth_dollars": -0.85,
        "growth_pct": -0.01,
        "free_cash": 7290,
        "deployed_capital": 2709.15,
        "cash_pct": 72.91,
        "invested_pct": 27.09,
        "open_count": 3,
        "analytics": {
          "OVERALL": {
            "total_closed": 3,
            "wins": 0,
            "losses": 3,
            "win_rate_pct": 0,
            "avg_win_pct": 0,
            "avg_loss_pct": 0,
            "reward_risk_ratio": 0,
            "total_pnl_pct": 0,
            "total_pnl_dollars": 0
          },
          "BY_ASSET": [
            {
              "key": "DRVN",
              "count": 1,
              "win_rate_pct": 0,
              "total_pnl_pct": 0,
              "total_pnl_dollars": 0
            },
            {
              "key": "MYND",
              "count": 1,
              "win_rate_pct": 0,
              "total_pnl_pct": 0,
              "total_pnl_dollars": 0
            },
            {
              "key": "PVH",
              "count": 1,
              "win_rate_pct": 0,
              "total_pnl_pct": 0,
              "total_pnl_dollars": 0
            }
          ],
          "BY_SOURCE": [
            {
              "key": "Seeking Alpha RSS",
              "count": 2,
              "win_rate_pct": 0,
              "avg_pnl_pct": 0
            },
            {
              "key": "Yahoo Finance RSS",
              "count": 1,
              "win_rate_pct": 0,
              "avg_pnl_pct": 0
            }
          ],
          "BY_CONFIDENCE": [
            {
              "key": "0.60-0.69",
              "count": 1,
              "win_rate_pct": 0
            },
            {
              "key": "0.70-0.79",
              "count": 2,
              "win_rate_pct": 0
            }
          ],
          "BY_EXIT_REASON": [
            {
              "key": "voided_pre_gate_bug",
              "count": 3,
              "win_rate_pct": 0
            }
          ],
          "BY_DIRECTION": [
            {
              "key": "SELL",
              "count": 3,
              "win_rate_pct": 0,
              "avg_win_pct": 0,
              "avg_loss_pct": 0
            }
          ],
          "BY_ALIGNMENT": [
            {
              "key": "aligned",
              "count": 2,
              "win_rate_pct": 0
            },
            {
              "key": "neutral",
              "count": 1,
              "win_rate_pct": 0
            }
          ],
          "BY_RSI_BAND": [
            {
              "key": "neutral (30-70)",
              "count": 3,
              "win_rate_pct": 0
            }
          ],
          "BY_TREND": [
            {
              "key": "above_ma20 (uptrend)",
              "count": 1,
              "win_rate_pct": 0
            },
            {
              "key": "below_ma20 (downtrend)",
              "count": 2,
              "win_rate_pct": 0
            }
          ],
          "BY_HOUR": [
            {
              "key": "14:00 MT",
              "count": 1,
              "win_rate_pct": 0
            },
            {
              "key": "15:00 MT",
              "count": 2,
              "win_rate_pct": 0
            }
          ],
          "AVG_HOLD_TIME": {
            "avg_minutes": 240.19,
            "avg_win_minutes": null,
            "avg_loss_minutes": null,
            "n": 3
          }
        },
        "closed": {
          "count": 3,
          "wins": 0,
          "losses": 0,
          "win_rate_pct": 0,
          "total_pnl_dollars": 0,
          "low_sample": true
        }
      },
      "sell_eod": {
        "portfolio": "news_plus_ta",
        "exit_rule": "sell_eod",
        "book_key": "news_plus_ta__sell_eod",
        "starting_balance": 10000,
        "total_equity": 9999.15,
        "growth_dollars": -0.85,
        "growth_pct": -0.01,
        "free_cash": 7290,
        "deployed_capital": 2709.15,
        "cash_pct": 72.91,
        "invested_pct": 27.09,
        "open_count": 3,
        "analytics": {
          "OVERALL": {
            "total_closed": 3,
            "wins": 0,
            "losses": 3,
            "win_rate_pct": 0,
            "avg_win_pct": 0,
            "avg_loss_pct": 0,
            "reward_risk_ratio": 0,
            "total_pnl_pct": 0,
            "total_pnl_dollars": 0
          },
          "BY_ASSET": [
            {
              "key": "DRVN",
              "count": 1,
              "win_rate_pct": 0,
              "total_pnl_pct": 0,
              "total_pnl_dollars": 0
            },
            {
              "key": "MYND",
              "count": 1,
              "win_rate_pct": 0,
              "total_pnl_pct": 0,
              "total_pnl_dollars": 0
            },
            {
              "key": "PVH",
              "count": 1,
              "win_rate_pct": 0,
              "total_pnl_pct": 0,
              "total_pnl_dollars": 0
            }
          ],
          "BY_SOURCE": [
            {
              "key": "Seeking Alpha RSS",
              "count": 2,
              "win_rate_pct": 0,
              "avg_pnl_pct": 0
            },
            {
              "key": "Yahoo Finance RSS",
              "count": 1,
              "win_rate_pct": 0,
              "avg_pnl_pct": 0
            }
          ],
          "BY_CONFIDENCE": [
            {
              "key": "0.60-0.69",
              "count": 1,
              "win_rate_pct": 0
            },
            {
              "key": "0.70-0.79",
              "count": 2,
              "win_rate_pct": 0
            }
          ],
          "BY_EXIT_REASON": [
            {
              "key": "voided_pre_gate_bug",
              "count": 3,
              "win_rate_pct": 0
            }
          ],
          "BY_DIRECTION": [
            {
              "key": "SELL",
              "count": 3,
              "win_rate_pct": 0,
              "avg_win_pct": 0,
              "avg_loss_pct": 0
            }
          ],
          "BY_ALIGNMENT": [
            {
              "key": "aligned",
              "count": 2,
              "win_rate_pct": 0
            },
            {
              "key": "neutral",
              "count": 1,
              "win_rate_pct": 0
            }
          ],
          "BY_RSI_BAND": [
            {
              "key": "neutral (30-70)",
              "count": 3,
              "win_rate_pct": 0
            }
          ],
          "BY_TREND": [
            {
              "key": "above_ma20 (uptrend)",
              "count": 1,
              "win_rate_pct": 0
            },
            {
              "key": "below_ma20 (downtrend)",
              "count": 2,
              "win_rate_pct": 0
            }
          ],
          "BY_HOUR": [
            {
              "key": "14:00 MT",
              "count": 1,
              "win_rate_pct": 0
            },
            {
              "key": "15:00 MT",
              "count": 2,
              "win_rate_pct": 0
            }
          ],
          "AVG_HOLD_TIME": {
            "avg_minutes": 240.19,
            "avg_win_minutes": null,
            "avg_loss_minutes": null,
            "n": 3
          }
        },
        "closed": {
          "count": 3,
          "wins": 0,
          "losses": 0,
          "win_rate_pct": 0,
          "total_pnl_dollars": 0,
          "low_sample": true
        }
      }
    },
    "mean_reversion": {
      "hold_24hr": {
        "portfolio": "mean_reversion",
        "exit_rule": "hold_24hr",
        "book_key": "mean_reversion__hold_24hr",
        "starting_balance": 10000,
        "total_equity": 10000,
        "growth_dollars": 0,
        "growth_pct": 0,
        "free_cash": 10000,
        "deployed_capital": 0,
        "cash_pct": 100,
        "invested_pct": 0,
        "open_count": 0,
        "analytics": {
          "OVERALL": {
            "total_closed": 1,
            "wins": 0,
            "losses": 1,
            "win_rate_pct": 0,
            "avg_win_pct": 0,
            "avg_loss_pct": 0,
            "reward_risk_ratio": 0,
            "total_pnl_pct": 0,
            "total_pnl_dollars": 0
          },
          "BY_ASSET": [
            {
              "key": "DRVN",
              "count": 1,
              "win_rate_pct": 0,
              "total_pnl_pct": 0,
              "total_pnl_dollars": 0
            }
          ],
          "BY_SOURCE": [
            {
              "key": "Seeking Alpha RSS",
              "count": 1,
              "win_rate_pct": 0,
              "avg_pnl_pct": 0
            }
          ],
          "BY_CONFIDENCE": [
            {
              "key": "0.60-0.69",
              "count": 1,
              "win_rate_pct": 0
            }
          ],
          "BY_EXIT_REASON": [
            {
              "key": "voided_pre_gate_bug",
              "count": 1,
              "win_rate_pct": 0
            }
          ],
          "BY_DIRECTION": [
            {
              "key": "SELL",
              "count": 1,
              "win_rate_pct": 0,
              "avg_win_pct": 0,
              "avg_loss_pct": 0
            }
          ],
          "BY_ALIGNMENT": [
            {
              "key": "aligned",
              "count": 1,
              "win_rate_pct": 0
            }
          ],
          "BY_RSI_BAND": [
            {
              "key": "neutral (30-70)",
              "count": 1,
              "win_rate_pct": 0
            }
          ],
          "BY_TREND": [
            {
              "key": "below_ma20 (downtrend)",
              "count": 1,
              "win_rate_pct": 0
            }
          ],
          "BY_HOUR": [
            {
              "key": "15:00 MT",
              "count": 1,
              "win_rate_pct": 0
            }
          ],
          "AVG_HOLD_TIME": {
            "avg_minutes": 230.22,
            "avg_win_minutes": null,
            "avg_loss_minutes": null,
            "n": 1
          }
        },
        "closed": {
          "count": 1,
          "wins": 0,
          "losses": 0,
          "win_rate_pct": 0,
          "total_pnl_dollars": 0,
          "low_sample": true
        }
      },
      "sell_eod": {
        "portfolio": "mean_reversion",
        "exit_rule": "sell_eod",
        "book_key": "mean_reversion__sell_eod",
        "starting_balance": 10000,
        "total_equity": 10000,
        "growth_dollars": 0,
        "growth_pct": 0,
        "free_cash": 10000,
        "deployed_capital": 0,
        "cash_pct": 100,
        "invested_pct": 0,
        "open_count": 0,
        "analytics": {
          "OVERALL": {
            "total_closed": 1,
            "wins": 0,
            "losses": 1,
            "win_rate_pct": 0,
            "avg_win_pct": 0,
            "avg_loss_pct": 0,
            "reward_risk_ratio": 0,
            "total_pnl_pct": 0,
            "total_pnl_dollars": 0
          },
          "BY_ASSET": [
            {
              "key": "DRVN",
              "count": 1,
              "win_rate_pct": 0,
              "total_pnl_pct": 0,
              "total_pnl_dollars": 0
            }
          ],
          "BY_SOURCE": [
            {
              "key": "Seeking Alpha RSS",
              "count": 1,
              "win_rate_pct": 0,
              "avg_pnl_pct": 0
            }
          ],
          "BY_CONFIDENCE": [
            {
              "key": "0.60-0.69",
              "count": 1,
              "win_rate_pct": 0
            }
          ],
          "BY_EXIT_REASON": [
            {
              "key": "voided_pre_gate_bug",
              "count": 1,
              "win_rate_pct": 0
            }
          ],
          "BY_DIRECTION": [
            {
              "key": "SELL",
              "count": 1,
              "win_rate_pct": 0,
              "avg_win_pct": 0,
              "avg_loss_pct": 0
            }
          ],
          "BY_ALIGNMENT": [
            {
              "key": "aligned",
              "count": 1,
              "win_rate_pct": 0
            }
          ],
          "BY_RSI_BAND": [
            {
              "key": "neutral (30-70)",
              "count": 1,
              "win_rate_pct": 0
            }
          ],
          "BY_TREND": [
            {
              "key": "below_ma20 (downtrend)",
              "count": 1,
              "win_rate_pct": 0
            }
          ],
          "BY_HOUR": [
            {
              "key": "15:00 MT",
              "count": 1,
              "win_rate_pct": 0
            }
          ],
          "AVG_HOLD_TIME": {
            "avg_minutes": 230.22,
            "avg_win_minutes": null,
            "avg_loss_minutes": null,
            "n": 1
          }
        },
        "closed": {
          "count": 1,
          "wins": 0,
          "losses": 0,
          "win_rate_pct": 0,
          "total_pnl_dollars": 0,
          "low_sample": true
        }
      }
    },
    "trend_strict": {
      "hold_24hr": {
        "portfolio": "trend_strict",
        "exit_rule": "hold_24hr",
        "book_key": "trend_strict__hold_24hr",
        "starting_balance": 10000,
        "total_equity": 10018.54,
        "growth_dollars": 18.54,
        "growth_pct": 0.19,
        "free_cash": 8100,
        "deployed_capital": 1918.54,
        "cash_pct": 80.85,
        "invested_pct": 19.15,
        "open_count": 2,
        "analytics": {
          "OVERALL": {
            "total_closed": 2,
            "wins": 0,
            "losses": 2,
            "win_rate_pct": 0,
            "avg_win_pct": 0,
            "avg_loss_pct": 0,
            "reward_risk_ratio": 0,
            "total_pnl_pct": 0,
            "total_pnl_dollars": 0
          },
          "BY_ASSET": [
            {
              "key": "DRVN",
              "count": 1,
              "win_rate_pct": 0,
              "total_pnl_pct": 0,
              "total_pnl_dollars": 0
            },
            {
              "key": "PVH",
              "count": 1,
              "win_rate_pct": 0,
              "total_pnl_pct": 0,
              "total_pnl_dollars": 0
            }
          ],
          "BY_SOURCE": [
            {
              "key": "Seeking Alpha RSS",
              "count": 1,
              "win_rate_pct": 0,
              "avg_pnl_pct": 0
            },
            {
              "key": "Yahoo Finance RSS",
              "count": 1,
              "win_rate_pct": 0,
              "avg_pnl_pct": 0
            }
          ],
          "BY_CONFIDENCE": [
            {
              "key": "0.60-0.69",
              "count": 1,
              "win_rate_pct": 0
            },
            {
              "key": "0.70-0.79",
              "count": 1,
              "win_rate_pct": 0
            }
          ],
          "BY_EXIT_REASON": [
            {
              "key": "voided_pre_gate_bug",
              "count": 2,
              "win_rate_pct": 0
            }
          ],
          "BY_DIRECTION": [
            {
              "key": "SELL",
              "count": 2,
              "win_rate_pct": 0,
              "avg_win_pct": 0,
              "avg_loss_pct": 0
            }
          ],
          "BY_ALIGNMENT": [
            {
              "key": "aligned",
              "count": 2,
              "win_rate_pct": 0
            }
          ],
          "BY_RSI_BAND": [
            {
              "key": "neutral (30-70)",
              "count": 2,
              "win_rate_pct": 0
            }
          ],
          "BY_TREND": [
            {
              "key": "below_ma20 (downtrend)",
              "count": 2,
              "win_rate_pct": 0
            }
          ],
          "BY_HOUR": [
            {
              "key": "14:00 MT",
              "count": 1,
              "win_rate_pct": 0
            },
            {
              "key": "15:00 MT",
              "count": 1,
              "win_rate_pct": 0
            }
          ],
          "AVG_HOLD_TIME": {
            "avg_minutes": 245.18,
            "avg_win_minutes": null,
            "avg_loss_minutes": null,
            "n": 2
          }
        },
        "closed": {
          "count": 2,
          "wins": 0,
          "losses": 0,
          "win_rate_pct": 0,
          "total_pnl_dollars": 0,
          "low_sample": true
        }
      },
      "sell_eod": {
        "portfolio": "trend_strict",
        "exit_rule": "sell_eod",
        "book_key": "trend_strict__sell_eod",
        "starting_balance": 10000,
        "total_equity": 10018.54,
        "growth_dollars": 18.54,
        "growth_pct": 0.19,
        "free_cash": 8100,
        "deployed_capital": 1918.54,
        "cash_pct": 80.85,
        "invested_pct": 19.15,
        "open_count": 2,
        "analytics": {
          "OVERALL": {
            "total_closed": 2,
            "wins": 0,
            "losses": 2,
            "win_rate_pct": 0,
            "avg_win_pct": 0,
            "avg_loss_pct": 0,
            "reward_risk_ratio": 0,
            "total_pnl_pct": 0,
            "total_pnl_dollars": 0
          },
          "BY_ASSET": [
            {
              "key": "DRVN",
              "count": 1,
              "win_rate_pct": 0,
              "total_pnl_pct": 0,
              "total_pnl_dollars": 0
            },
            {
              "key": "PVH",
              "count": 1,
              "win_rate_pct": 0,
              "total_pnl_pct": 0,
              "total_pnl_dollars": 0
            }
          ],
          "BY_SOURCE": [
            {
              "key": "Seeking Alpha RSS",
              "count": 1,
              "win_rate_pct": 0,
              "avg_pnl_pct": 0
            },
            {
              "key": "Yahoo Finance RSS",
              "count": 1,
              "win_rate_pct": 0,
              "avg_pnl_pct": 0
            }
          ],
          "BY_CONFIDENCE": [
            {
              "key": "0.60-0.69",
              "count": 1,
              "win_rate_pct": 0
            },
            {
              "key": "0.70-0.79",
              "count": 1,
              "win_rate_pct": 0
            }
          ],
          "BY_EXIT_REASON": [
            {
              "key": "voided_pre_gate_bug",
              "count": 2,
              "win_rate_pct": 0
            }
          ],
          "BY_DIRECTION": [
            {
              "key": "SELL",
              "count": 2,
              "win_rate_pct": 0,
              "avg_win_pct": 0,
              "avg_loss_pct": 0
            }
          ],
          "BY_ALIGNMENT": [
            {
              "key": "aligned",
              "count": 2,
              "win_rate_pct": 0
            }
          ],
          "BY_RSI_BAND": [
            {
              "key": "neutral (30-70)",
              "count": 2,
              "win_rate_pct": 0
            }
          ],
          "BY_TREND": [
            {
              "key": "below_ma20 (downtrend)",
              "count": 2,
              "win_rate_pct": 0
            }
          ],
          "BY_HOUR": [
            {
              "key": "14:00 MT",
              "count": 1,
              "win_rate_pct": 0
            },
            {
              "key": "15:00 MT",
              "count": 1,
              "win_rate_pct": 0
            }
          ],
          "AVG_HOLD_TIME": {
            "avg_minutes": 245.18,
            "avg_win_minutes": null,
            "avg_loss_minutes": null,
            "n": 2
          }
        },
        "closed": {
          "count": 2,
          "wins": 0,
          "losses": 0,
          "win_rate_pct": 0,
          "total_pnl_dollars": 0,
          "low_sample": true
        }
      }
    },
    "strict": {
      "hold_24hr": {
        "portfolio": "strict",
        "exit_rule": "hold_24hr",
        "book_key": "strict__hold_24hr",
        "starting_balance": 10000,
        "total_equity": 10000,
        "growth_dollars": 0,
        "growth_pct": 0,
        "free_cash": 10000,
        "deployed_capital": 0,
        "cash_pct": 100,
        "invested_pct": 0,
        "open_count": 0,
        "analytics": {
          "OVERALL": {
            "total_closed": 0,
            "wins": 0,
            "losses": 0,
            "win_rate_pct": 0,
            "avg_win_pct": 0,
            "avg_loss_pct": 0,
            "reward_risk_ratio": 0,
            "total_pnl_pct": 0,
            "total_pnl_dollars": 0
          },
          "BY_ASSET": [],
          "BY_SOURCE": [],
          "BY_CONFIDENCE": [],
          "BY_EXIT_REASON": [],
          "BY_DIRECTION": [],
          "BY_ALIGNMENT": [],
          "BY_RSI_BAND": [],
          "BY_TREND": [],
          "BY_HOUR": [],
          "AVG_HOLD_TIME": {
            "avg_minutes": null,
            "avg_win_minutes": null,
            "avg_loss_minutes": null,
            "n": 0
          }
        },
        "closed": {
          "count": 0,
          "wins": 0,
          "losses": 0,
          "win_rate_pct": null,
          "total_pnl_dollars": 0,
          "low_sample": true
        }
      },
      "sell_eod": {
        "portfolio": "strict",
        "exit_rule": "sell_eod",
        "book_key": "strict__sell_eod",
        "starting_balance": 10000,
        "total_equity": 10000,
        "growth_dollars": 0,
        "growth_pct": 0,
        "free_cash": 10000,
        "deployed_capital": 0,
        "cash_pct": 100,
        "invested_pct": 0,
        "open_count": 0,
        "analytics": {
          "OVERALL": {
            "total_closed": 0,
            "wins": 0,
            "losses": 0,
            "win_rate_pct": 0,
            "avg_win_pct": 0,
            "avg_loss_pct": 0,
            "reward_risk_ratio": 0,
            "total_pnl_pct": 0,
            "total_pnl_dollars": 0
          },
          "BY_ASSET": [],
          "BY_SOURCE": [],
          "BY_CONFIDENCE": [],
          "BY_EXIT_REASON": [],
          "BY_DIRECTION": [],
          "BY_ALIGNMENT": [],
          "BY_RSI_BAND": [],
          "BY_TREND": [],
          "BY_HOUR": [],
          "AVG_HOLD_TIME": {
            "avg_minutes": null,
            "avg_win_minutes": null,
            "avg_loss_minutes": null,
            "n": 0
          }
        },
        "closed": {
          "count": 0,
          "wins": 0,
          "losses": 0,
          "win_rate_pct": null,
          "total_pnl_dollars": 0,
          "low_sample": true
        }
      }
    }
  },
  "open_positions": [
    {
      "book_key": "news_only__hold_24hr",
      "portfolio": "news_only",
      "exit_rule": "hold_24hr",
      "asset": "ARCB",
      "direction": "LONG",
      "stake_amount": 1000,
      "shares": 6.512961,
      "entry_price": 153.54,
      "entry_time": "2026-06-05T15:01:57.985Z"
    },
    {
      "book_key": "news_only__sell_eod",
      "portfolio": "news_only",
      "exit_rule": "sell_eod",
      "asset": "ARCB",
      "direction": "LONG",
      "stake_amount": 1000,
      "shares": 6.512961,
      "entry_price": 153.54,
      "entry_time": "2026-06-05T15:01:57.985Z"
    },
    {
      "book_key": "news_only__hold_24hr",
      "portfolio": "news_only",
      "exit_rule": "hold_24hr",
      "asset": "RBRK",
      "direction": "LONG",
      "stake_amount": 900,
      "shares": 12.202563,
      "entry_price": 73.755,
      "entry_time": "2026-06-05T15:01:57.985Z"
    },
    {
      "book_key": "news_only__sell_eod",
      "portfolio": "news_only",
      "exit_rule": "sell_eod",
      "asset": "RBRK",
      "direction": "LONG",
      "stake_amount": 900,
      "shares": 12.202563,
      "entry_price": 73.755,
      "entry_time": "2026-06-05T15:01:57.985Z"
    },
    {
      "book_key": "news_plus_ta__hold_24hr",
      "portfolio": "news_plus_ta",
      "exit_rule": "hold_24hr",
      "asset": "RBRK",
      "direction": "LONG",
      "stake_amount": 1000,
      "shares": 13.558403,
      "entry_price": 73.755,
      "entry_time": "2026-06-05T15:01:58.130Z"
    },
    {
      "book_key": "news_plus_ta__sell_eod",
      "portfolio": "news_plus_ta",
      "exit_rule": "sell_eod",
      "asset": "RBRK",
      "direction": "LONG",
      "stake_amount": 1000,
      "shares": 13.558403,
      "entry_price": 73.755,
      "entry_time": "2026-06-05T15:01:58.130Z"
    },
    {
      "book_key": "trend_strict__hold_24hr",
      "portfolio": "trend_strict",
      "exit_rule": "hold_24hr",
      "asset": "ARCB",
      "direction": "LONG",
      "stake_amount": 1000,
      "shares": 6.512961,
      "entry_price": 153.54,
      "entry_time": "2026-06-05T15:01:58.271Z"
    },
    {
      "book_key": "trend_strict__sell_eod",
      "portfolio": "trend_strict",
      "exit_rule": "sell_eod",
      "asset": "ARCB",
      "direction": "LONG",
      "stake_amount": 1000,
      "shares": 6.512961,
      "entry_price": 153.54,
      "entry_time": "2026-06-05T15:01:58.271Z"
    },
    {
      "book_key": "news_only__hold_24hr",
      "portfolio": "news_only",
      "exit_rule": "hold_24hr",
      "asset": "GSC",
      "direction": "LONG",
      "stake_amount": 810,
      "shares": 13.07295,
      "entry_price": 61.96,
      "entry_time": "2026-06-05T17:01:32.678Z"
    },
    {
      "book_key": "news_only__sell_eod",
      "portfolio": "news_only",
      "exit_rule": "sell_eod",
      "asset": "GSC",
      "direction": "LONG",
      "stake_amount": 810,
      "shares": 13.07295,
      "entry_price": 61.96,
      "entry_time": "2026-06-05T17:01:32.678Z"
    },
    {
      "book_key": "news_plus_ta__hold_24hr",
      "portfolio": "news_plus_ta",
      "exit_rule": "hold_24hr",
      "asset": "GSC",
      "direction": "LONG",
      "stake_amount": 900,
      "shares": 14.5255,
      "entry_price": 61.96,
      "entry_time": "2026-06-05T17:01:32.828Z"
    },
    {
      "book_key": "news_plus_ta__sell_eod",
      "portfolio": "news_plus_ta",
      "exit_rule": "sell_eod",
      "asset": "GSC",
      "direction": "LONG",
      "stake_amount": 900,
      "shares": 14.5255,
      "entry_price": 61.96,
      "entry_time": "2026-06-05T17:01:32.828Z"
    },
    {
      "book_key": "news_only__hold_24hr",
      "portfolio": "news_only",
      "exit_rule": "hold_24hr",
      "asset": "SMMT",
      "direction": "LONG",
      "stake_amount": 729,
      "shares": 49.490835,
      "entry_price": 14.73,
      "entry_time": "2026-06-05T18:31:14.079Z"
    },
    {
      "book_key": "news_only__sell_eod",
      "portfolio": "news_only",
      "exit_rule": "sell_eod",
      "asset": "SMMT",
      "direction": "LONG",
      "stake_amount": 729,
      "shares": 49.490835,
      "entry_price": 14.73,
      "entry_time": "2026-06-05T18:31:14.079Z"
    },
    {
      "book_key": "news_only__hold_24hr",
      "portfolio": "news_only",
      "exit_rule": "hold_24hr",
      "asset": "MIRM",
      "direction": "LONG",
      "stake_amount": 656.1,
      "shares": 7.100649,
      "entry_price": 92.4,
      "entry_time": "2026-06-05T18:31:14.079Z"
    },
    {
      "book_key": "news_only__hold_24hr",
      "portfolio": "news_only",
      "exit_rule": "hold_24hr",
      "asset": "AVGO",
      "direction": "SHORT",
      "stake_amount": 590.49,
      "shares": 1.516468,
      "entry_price": 389.385,
      "entry_time": "2026-06-05T19:30:22.180Z"
    },
    {
      "book_key": "news_only__sell_eod",
      "portfolio": "news_only",
      "exit_rule": "sell_eod",
      "asset": "AVGO",
      "direction": "SHORT",
      "stake_amount": 590.49,
      "shares": 1.516468,
      "entry_price": 389.385,
      "entry_time": "2026-06-05T19:30:22.180Z"
    },
    {
      "book_key": "news_plus_ta__hold_24hr",
      "portfolio": "news_plus_ta",
      "exit_rule": "hold_24hr",
      "asset": "AVGO",
      "direction": "SHORT",
      "stake_amount": 810,
      "shares": 2.080203,
      "entry_price": 389.385,
      "entry_time": "2026-06-05T19:30:22.325Z"
    },
    {
      "book_key": "news_plus_ta__sell_eod",
      "portfolio": "news_plus_ta",
      "exit_rule": "sell_eod",
      "asset": "AVGO",
      "direction": "SHORT",
      "stake_amount": 810,
      "shares": 2.080203,
      "entry_price": 389.385,
      "entry_time": "2026-06-05T19:30:22.325Z"
    },
    {
      "book_key": "trend_strict__hold_24hr",
      "portfolio": "trend_strict",
      "exit_rule": "hold_24hr",
      "asset": "AVGO",
      "direction": "SHORT",
      "stake_amount": 900,
      "shares": 2.311337,
      "entry_price": 389.385,
      "entry_time": "2026-06-05T19:30:22.465Z"
    },
    {
      "book_key": "trend_strict__sell_eod",
      "portfolio": "trend_strict",
      "exit_rule": "sell_eod",
      "asset": "AVGO",
      "direction": "SHORT",
      "stake_amount": 900,
      "shares": 2.311337,
      "entry_price": 389.385,
      "entry_time": "2026-06-05T19:30:22.465Z"
    }
  ],
  "low_sample_threshold": 20
}