{
  "generated_at": "2026-06-11T16:00:11.321Z",
  "model": "10-account (5 strategies x 2 exit rules)",
  "totals": {
    "equity": 80049.62,
    "starting": 80000,
    "pnl_dollars": 49.62,
    "pnl_pct": 0.06,
    "open_positions": 32,
    "book_count": 8
  },
  "strategies": [
    "news_only",
    "news_plus_ta",
    "mean_reversion",
    "trend_strict"
  ],
  "exit_rules": [
    "hold_24hr",
    "sell_eod"
  ],
  "books": [
    {
      "portfolio": "mean_reversion",
      "exit_rule": "hold_24hr",
      "book_key": "mean_reversion__hold_24hr",
      "starting_balance": 10000,
      "total_equity": 10012.62,
      "growth_dollars": 12.62,
      "growth_pct": 0.13,
      "free_cash": 8100,
      "deployed_capital": 1912.62,
      "cash_pct": 80.9,
      "invested_pct": 19.1,
      "open_count": 2,
      "analytics": {
        "OVERALL": {
          "total_closed": 0,
          "wins": 0,
          "losses": 0,
          "win_rate_pct": 0,
          "avg_win_pct": 0,
          "avg_loss_pct": 0,
          "reward_risk_ratio": 0,
          "total_pnl_pct": 0,
          "total_pnl_dollars": 0
        },
        "BY_ASSET": [],
        "BY_SOURCE": [],
        "BY_CONFIDENCE": [],
        "BY_EXIT_REASON": [],
        "BY_DIRECTION": [],
        "BY_ALIGNMENT": [],
        "BY_RSI_BAND": [],
        "BY_TREND": [],
        "BY_HOUR": [],
        "AVG_HOLD_TIME": {
          "avg_minutes": null,
          "avg_win_minutes": null,
          "avg_loss_minutes": null,
          "n": 0
        }
      },
      "closed": {
        "count": 0,
        "wins": 0,
        "losses": 0,
        "win_rate_pct": null,
        "total_pnl_dollars": 0,
        "low_sample": true
      }
    },
    {
      "portfolio": "mean_reversion",
      "exit_rule": "sell_eod",
      "book_key": "mean_reversion__sell_eod",
      "starting_balance": 10000,
      "total_equity": 10012.62,
      "growth_dollars": 12.62,
      "growth_pct": 0.13,
      "free_cash": 8100,
      "deployed_capital": 1912.62,
      "cash_pct": 80.9,
      "invested_pct": 19.1,
      "open_count": 2,
      "analytics": {
        "OVERALL": {
          "total_closed": 0,
          "wins": 0,
          "losses": 0,
          "win_rate_pct": 0,
          "avg_win_pct": 0,
          "avg_loss_pct": 0,
          "reward_risk_ratio": 0,
          "total_pnl_pct": 0,
          "total_pnl_dollars": 0
        },
        "BY_ASSET": [],
        "BY_SOURCE": [],
        "BY_CONFIDENCE": [],
        "BY_EXIT_REASON": [],
        "BY_DIRECTION": [],
        "BY_ALIGNMENT": [],
        "BY_RSI_BAND": [],
        "BY_TREND": [],
        "BY_HOUR": [],
        "AVG_HOLD_TIME": {
          "avg_minutes": null,
          "avg_win_minutes": null,
          "avg_loss_minutes": null,
          "n": 0
        }
      },
      "closed": {
        "count": 0,
        "wins": 0,
        "losses": 0,
        "win_rate_pct": null,
        "total_pnl_dollars": 0,
        "low_sample": true
      }
    },
    {
      "portfolio": "news_only",
      "exit_rule": "hold_24hr",
      "book_key": "news_only__hold_24hr",
      "starting_balance": 10000,
      "total_equity": 9996.03,
      "growth_dollars": -3.97,
      "growth_pct": -0.04,
      "free_cash": 4304.67,
      "deployed_capital": 4681.62,
      "cash_pct": 47.9,
      "invested_pct": 52.1,
      "open_count": 8,
      "analytics": {
        "OVERALL": {
          "total_closed": 0,
          "wins": 0,
          "losses": 0,
          "win_rate_pct": 0,
          "avg_win_pct": 0,
          "avg_loss_pct": 0,
          "reward_risk_ratio": 0,
          "total_pnl_pct": 0,
          "total_pnl_dollars": 0
        },
        "BY_ASSET": [],
        "BY_SOURCE": [],
        "BY_CONFIDENCE": [],
        "BY_EXIT_REASON": [],
        "BY_DIRECTION": [],
        "BY_ALIGNMENT": [],
        "BY_RSI_BAND": [],
        "BY_TREND": [],
        "BY_HOUR": [],
        "AVG_HOLD_TIME": {
          "avg_minutes": null,
          "avg_win_minutes": null,
          "avg_loss_minutes": null,
          "n": 0
        }
      },
      "closed": {
        "count": 0,
        "wins": 0,
        "losses": 0,
        "win_rate_pct": null,
        "total_pnl_dollars": 0,
        "low_sample": true
      }
    },
    {
      "portfolio": "news_only",
      "exit_rule": "sell_eod",
      "book_key": "news_only__sell_eod",
      "starting_balance": 10000,
      "total_equity": 9996.03,
      "growth_dollars": -3.97,
      "growth_pct": -0.04,
      "free_cash": 4304.67,
      "deployed_capital": 4681.62,
      "cash_pct": 47.9,
      "invested_pct": 52.1,
      "open_count": 8,
      "analytics": {
        "OVERALL": {
          "total_closed": 0,
          "wins": 0,
          "losses": 0,
          "win_rate_pct": 0,
          "avg_win_pct": 0,
          "avg_loss_pct": 0,
          "reward_risk_ratio": 0,
          "total_pnl_pct": 0,
          "total_pnl_dollars": 0
        },
        "BY_ASSET": [],
        "BY_SOURCE": [],
        "BY_CONFIDENCE": [],
        "BY_EXIT_REASON": [],
        "BY_DIRECTION": [],
        "BY_ALIGNMENT": [],
        "BY_RSI_BAND": [],
        "BY_TREND": [],
        "BY_HOUR": [],
        "AVG_HOLD_TIME": {
          "avg_minutes": null,
          "avg_win_minutes": null,
          "avg_loss_minutes": null,
          "n": 0
        }
      },
      "closed": {
        "count": 0,
        "wins": 0,
        "losses": 0,
        "win_rate_pct": null,
        "total_pnl_dollars": 0,
        "low_sample": true
      }
    },
    {
      "portfolio": "news_plus_ta",
      "exit_rule": "hold_24hr",
      "book_key": "news_plus_ta__hold_24hr",
      "starting_balance": 10000,
      "total_equity": 10003.54,
      "growth_dollars": 3.54,
      "growth_pct": 0.04,
      "free_cash": 6561,
      "deployed_capital": 3442.54,
      "cash_pct": 65.59,
      "invested_pct": 34.41,
      "open_count": 4,
      "analytics": {
        "OVERALL": {
          "total_closed": 0,
          "wins": 0,
          "losses": 0,
          "win_rate_pct": 0,
          "avg_win_pct": 0,
          "avg_loss_pct": 0,
          "reward_risk_ratio": 0,
          "total_pnl_pct": 0,
          "total_pnl_dollars": 0
        },
        "BY_ASSET": [],
        "BY_SOURCE": [],
        "BY_CONFIDENCE": [],
        "BY_EXIT_REASON": [],
        "BY_DIRECTION": [],
        "BY_ALIGNMENT": [],
        "BY_RSI_BAND": [],
        "BY_TREND": [],
        "BY_HOUR": [],
        "AVG_HOLD_TIME": {
          "avg_minutes": null,
          "avg_win_minutes": null,
          "avg_loss_minutes": null,
          "n": 0
        }
      },
      "closed": {
        "count": 0,
        "wins": 0,
        "losses": 0,
        "win_rate_pct": null,
        "total_pnl_dollars": 0,
        "low_sample": true
      }
    },
    {
      "portfolio": "news_plus_ta",
      "exit_rule": "sell_eod",
      "book_key": "news_plus_ta__sell_eod",
      "starting_balance": 10000,
      "total_equity": 10003.54,
      "growth_dollars": 3.54,
      "growth_pct": 0.04,
      "free_cash": 6561,
      "deployed_capital": 3442.54,
      "cash_pct": 65.59,
      "invested_pct": 34.41,
      "open_count": 4,
      "analytics": {
        "OVERALL": {
          "total_closed": 0,
          "wins": 0,
          "losses": 0,
          "win_rate_pct": 0,
          "avg_win_pct": 0,
          "avg_loss_pct": 0,
          "reward_risk_ratio": 0,
          "total_pnl_pct": 0,
          "total_pnl_dollars": 0
        },
        "BY_ASSET": [],
        "BY_SOURCE": [],
        "BY_CONFIDENCE": [],
        "BY_EXIT_REASON": [],
        "BY_DIRECTION": [],
        "BY_ALIGNMENT": [],
        "BY_RSI_BAND": [],
        "BY_TREND": [],
        "BY_HOUR": [],
        "AVG_HOLD_TIME": {
          "avg_minutes": null,
          "avg_win_minutes": null,
          "avg_loss_minutes": null,
          "n": 0
        }
      },
      "closed": {
        "count": 0,
        "wins": 0,
        "losses": 0,
        "win_rate_pct": null,
        "total_pnl_dollars": 0,
        "low_sample": true
      }
    },
    {
      "portfolio": "trend_strict",
      "exit_rule": "hold_24hr",
      "book_key": "trend_strict__hold_24hr",
      "starting_balance": 10000,
      "total_equity": 10012.62,
      "growth_dollars": 12.62,
      "growth_pct": 0.13,
      "free_cash": 8100,
      "deployed_capital": 1912.62,
      "cash_pct": 80.9,
      "invested_pct": 19.1,
      "open_count": 2,
      "analytics": {
        "OVERALL": {
          "total_closed": 0,
          "wins": 0,
          "losses": 0,
          "win_rate_pct": 0,
          "avg_win_pct": 0,
          "avg_loss_pct": 0,
          "reward_risk_ratio": 0,
          "total_pnl_pct": 0,
          "total_pnl_dollars": 0
        },
        "BY_ASSET": [],
        "BY_SOURCE": [],
        "BY_CONFIDENCE": [],
        "BY_EXIT_REASON": [],
        "BY_DIRECTION": [],
        "BY_ALIGNMENT": [],
        "BY_RSI_BAND": [],
        "BY_TREND": [],
        "BY_HOUR": [],
        "AVG_HOLD_TIME": {
          "avg_minutes": null,
          "avg_win_minutes": null,
          "avg_loss_minutes": null,
          "n": 0
        }
      },
      "closed": {
        "count": 0,
        "wins": 0,
        "losses": 0,
        "win_rate_pct": null,
        "total_pnl_dollars": 0,
        "low_sample": true
      }
    },
    {
      "portfolio": "trend_strict",
      "exit_rule": "sell_eod",
      "book_key": "trend_strict__sell_eod",
      "starting_balance": 10000,
      "total_equity": 10012.62,
      "growth_dollars": 12.62,
      "growth_pct": 0.13,
      "free_cash": 8100,
      "deployed_capital": 1912.62,
      "cash_pct": 80.9,
      "invested_pct": 19.1,
      "open_count": 2,
      "analytics": {
        "OVERALL": {
          "total_closed": 0,
          "wins": 0,
          "losses": 0,
          "win_rate_pct": 0,
          "avg_win_pct": 0,
          "avg_loss_pct": 0,
          "reward_risk_ratio": 0,
          "total_pnl_pct": 0,
          "total_pnl_dollars": 0
        },
        "BY_ASSET": [],
        "BY_SOURCE": [],
        "BY_CONFIDENCE": [],
        "BY_EXIT_REASON": [],
        "BY_DIRECTION": [],
        "BY_ALIGNMENT": [],
        "BY_RSI_BAND": [],
        "BY_TREND": [],
        "BY_HOUR": [],
        "AVG_HOLD_TIME": {
          "avg_minutes": null,
          "avg_win_minutes": null,
          "avg_loss_minutes": null,
          "n": 0
        }
      },
      "closed": {
        "count": 0,
        "wins": 0,
        "losses": 0,
        "win_rate_pct": null,
        "total_pnl_dollars": 0,
        "low_sample": true
      }
    }
  ],
  "grid": {
    "news_only": {
      "hold_24hr": {
        "portfolio": "news_only",
        "exit_rule": "hold_24hr",
        "book_key": "news_only__hold_24hr",
        "starting_balance": 10000,
        "total_equity": 9996.03,
        "growth_dollars": -3.97,
        "growth_pct": -0.04,
        "free_cash": 4304.67,
        "deployed_capital": 4681.62,
        "cash_pct": 47.9,
        "invested_pct": 52.1,
        "open_count": 8,
        "analytics": {
          "OVERALL": {
            "total_closed": 0,
            "wins": 0,
            "losses": 0,
            "win_rate_pct": 0,
            "avg_win_pct": 0,
            "avg_loss_pct": 0,
            "reward_risk_ratio": 0,
            "total_pnl_pct": 0,
            "total_pnl_dollars": 0
          },
          "BY_ASSET": [],
          "BY_SOURCE": [],
          "BY_CONFIDENCE": [],
          "BY_EXIT_REASON": [],
          "BY_DIRECTION": [],
          "BY_ALIGNMENT": [],
          "BY_RSI_BAND": [],
          "BY_TREND": [],
          "BY_HOUR": [],
          "AVG_HOLD_TIME": {
            "avg_minutes": null,
            "avg_win_minutes": null,
            "avg_loss_minutes": null,
            "n": 0
          }
        },
        "closed": {
          "count": 0,
          "wins": 0,
          "losses": 0,
          "win_rate_pct": null,
          "total_pnl_dollars": 0,
          "low_sample": true
        }
      },
      "sell_eod": {
        "portfolio": "news_only",
        "exit_rule": "sell_eod",
        "book_key": "news_only__sell_eod",
        "starting_balance": 10000,
        "total_equity": 9996.03,
        "growth_dollars": -3.97,
        "growth_pct": -0.04,
        "free_cash": 4304.67,
        "deployed_capital": 4681.62,
        "cash_pct": 47.9,
        "invested_pct": 52.1,
        "open_count": 8,
        "analytics": {
          "OVERALL": {
            "total_closed": 0,
            "wins": 0,
            "losses": 0,
            "win_rate_pct": 0,
            "avg_win_pct": 0,
            "avg_loss_pct": 0,
            "reward_risk_ratio": 0,
            "total_pnl_pct": 0,
            "total_pnl_dollars": 0
          },
          "BY_ASSET": [],
          "BY_SOURCE": [],
          "BY_CONFIDENCE": [],
          "BY_EXIT_REASON": [],
          "BY_DIRECTION": [],
          "BY_ALIGNMENT": [],
          "BY_RSI_BAND": [],
          "BY_TREND": [],
          "BY_HOUR": [],
          "AVG_HOLD_TIME": {
            "avg_minutes": null,
            "avg_win_minutes": null,
            "avg_loss_minutes": null,
            "n": 0
          }
        },
        "closed": {
          "count": 0,
          "wins": 0,
          "losses": 0,
          "win_rate_pct": null,
          "total_pnl_dollars": 0,
          "low_sample": true
        }
      }
    },
    "news_plus_ta": {
      "hold_24hr": {
        "portfolio": "news_plus_ta",
        "exit_rule": "hold_24hr",
        "book_key": "news_plus_ta__hold_24hr",
        "starting_balance": 10000,
        "total_equity": 10003.54,
        "growth_dollars": 3.54,
        "growth_pct": 0.04,
        "free_cash": 6561,
        "deployed_capital": 3442.54,
        "cash_pct": 65.59,
        "invested_pct": 34.41,
        "open_count": 4,
        "analytics": {
          "OVERALL": {
            "total_closed": 0,
            "wins": 0,
            "losses": 0,
            "win_rate_pct": 0,
            "avg_win_pct": 0,
            "avg_loss_pct": 0,
            "reward_risk_ratio": 0,
            "total_pnl_pct": 0,
            "total_pnl_dollars": 0
          },
          "BY_ASSET": [],
          "BY_SOURCE": [],
          "BY_CONFIDENCE": [],
          "BY_EXIT_REASON": [],
          "BY_DIRECTION": [],
          "BY_ALIGNMENT": [],
          "BY_RSI_BAND": [],
          "BY_TREND": [],
          "BY_HOUR": [],
          "AVG_HOLD_TIME": {
            "avg_minutes": null,
            "avg_win_minutes": null,
            "avg_loss_minutes": null,
            "n": 0
          }
        },
        "closed": {
          "count": 0,
          "wins": 0,
          "losses": 0,
          "win_rate_pct": null,
          "total_pnl_dollars": 0,
          "low_sample": true
        }
      },
      "sell_eod": {
        "portfolio": "news_plus_ta",
        "exit_rule": "sell_eod",
        "book_key": "news_plus_ta__sell_eod",
        "starting_balance": 10000,
        "total_equity": 10003.54,
        "growth_dollars": 3.54,
        "growth_pct": 0.04,
        "free_cash": 6561,
        "deployed_capital": 3442.54,
        "cash_pct": 65.59,
        "invested_pct": 34.41,
        "open_count": 4,
        "analytics": {
          "OVERALL": {
            "total_closed": 0,
            "wins": 0,
            "losses": 0,
            "win_rate_pct": 0,
            "avg_win_pct": 0,
            "avg_loss_pct": 0,
            "reward_risk_ratio": 0,
            "total_pnl_pct": 0,
            "total_pnl_dollars": 0
          },
          "BY_ASSET": [],
          "BY_SOURCE": [],
          "BY_CONFIDENCE": [],
          "BY_EXIT_REASON": [],
          "BY_DIRECTION": [],
          "BY_ALIGNMENT": [],
          "BY_RSI_BAND": [],
          "BY_TREND": [],
          "BY_HOUR": [],
          "AVG_HOLD_TIME": {
            "avg_minutes": null,
            "avg_win_minutes": null,
            "avg_loss_minutes": null,
            "n": 0
          }
        },
        "closed": {
          "count": 0,
          "wins": 0,
          "losses": 0,
          "win_rate_pct": null,
          "total_pnl_dollars": 0,
          "low_sample": true
        }
      }
    },
    "mean_reversion": {
      "hold_24hr": {
        "portfolio": "mean_reversion",
        "exit_rule": "hold_24hr",
        "book_key": "mean_reversion__hold_24hr",
        "starting_balance": 10000,
        "total_equity": 10012.62,
        "growth_dollars": 12.62,
        "growth_pct": 0.13,
        "free_cash": 8100,
        "deployed_capital": 1912.62,
        "cash_pct": 80.9,
        "invested_pct": 19.1,
        "open_count": 2,
        "analytics": {
          "OVERALL": {
            "total_closed": 0,
            "wins": 0,
            "losses": 0,
            "win_rate_pct": 0,
            "avg_win_pct": 0,
            "avg_loss_pct": 0,
            "reward_risk_ratio": 0,
            "total_pnl_pct": 0,
            "total_pnl_dollars": 0
          },
          "BY_ASSET": [],
          "BY_SOURCE": [],
          "BY_CONFIDENCE": [],
          "BY_EXIT_REASON": [],
          "BY_DIRECTION": [],
          "BY_ALIGNMENT": [],
          "BY_RSI_BAND": [],
          "BY_TREND": [],
          "BY_HOUR": [],
          "AVG_HOLD_TIME": {
            "avg_minutes": null,
            "avg_win_minutes": null,
            "avg_loss_minutes": null,
            "n": 0
          }
        },
        "closed": {
          "count": 0,
          "wins": 0,
          "losses": 0,
          "win_rate_pct": null,
          "total_pnl_dollars": 0,
          "low_sample": true
        }
      },
      "sell_eod": {
        "portfolio": "mean_reversion",
        "exit_rule": "sell_eod",
        "book_key": "mean_reversion__sell_eod",
        "starting_balance": 10000,
        "total_equity": 10012.62,
        "growth_dollars": 12.62,
        "growth_pct": 0.13,
        "free_cash": 8100,
        "deployed_capital": 1912.62,
        "cash_pct": 80.9,
        "invested_pct": 19.1,
        "open_count": 2,
        "analytics": {
          "OVERALL": {
            "total_closed": 0,
            "wins": 0,
            "losses": 0,
            "win_rate_pct": 0,
            "avg_win_pct": 0,
            "avg_loss_pct": 0,
            "reward_risk_ratio": 0,
            "total_pnl_pct": 0,
            "total_pnl_dollars": 0
          },
          "BY_ASSET": [],
          "BY_SOURCE": [],
          "BY_CONFIDENCE": [],
          "BY_EXIT_REASON": [],
          "BY_DIRECTION": [],
          "BY_ALIGNMENT": [],
          "BY_RSI_BAND": [],
          "BY_TREND": [],
          "BY_HOUR": [],
          "AVG_HOLD_TIME": {
            "avg_minutes": null,
            "avg_win_minutes": null,
            "avg_loss_minutes": null,
            "n": 0
          }
        },
        "closed": {
          "count": 0,
          "wins": 0,
          "losses": 0,
          "win_rate_pct": null,
          "total_pnl_dollars": 0,
          "low_sample": true
        }
      }
    },
    "trend_strict": {
      "hold_24hr": {
        "portfolio": "trend_strict",
        "exit_rule": "hold_24hr",
        "book_key": "trend_strict__hold_24hr",
        "starting_balance": 10000,
        "total_equity": 10012.62,
        "growth_dollars": 12.62,
        "growth_pct": 0.13,
        "free_cash": 8100,
        "deployed_capital": 1912.62,
        "cash_pct": 80.9,
        "invested_pct": 19.1,
        "open_count": 2,
        "analytics": {
          "OVERALL": {
            "total_closed": 0,
            "wins": 0,
            "losses": 0,
            "win_rate_pct": 0,
            "avg_win_pct": 0,
            "avg_loss_pct": 0,
            "reward_risk_ratio": 0,
            "total_pnl_pct": 0,
            "total_pnl_dollars": 0
          },
          "BY_ASSET": [],
          "BY_SOURCE": [],
          "BY_CONFIDENCE": [],
          "BY_EXIT_REASON": [],
          "BY_DIRECTION": [],
          "BY_ALIGNMENT": [],
          "BY_RSI_BAND": [],
          "BY_TREND": [],
          "BY_HOUR": [],
          "AVG_HOLD_TIME": {
            "avg_minutes": null,
            "avg_win_minutes": null,
            "avg_loss_minutes": null,
            "n": 0
          }
        },
        "closed": {
          "count": 0,
          "wins": 0,
          "losses": 0,
          "win_rate_pct": null,
          "total_pnl_dollars": 0,
          "low_sample": true
        }
      },
      "sell_eod": {
        "portfolio": "trend_strict",
        "exit_rule": "sell_eod",
        "book_key": "trend_strict__sell_eod",
        "starting_balance": 10000,
        "total_equity": 10012.62,
        "growth_dollars": 12.62,
        "growth_pct": 0.13,
        "free_cash": 8100,
        "deployed_capital": 1912.62,
        "cash_pct": 80.9,
        "invested_pct": 19.1,
        "open_count": 2,
        "analytics": {
          "OVERALL": {
            "total_closed": 0,
            "wins": 0,
            "losses": 0,
            "win_rate_pct": 0,
            "avg_win_pct": 0,
            "avg_loss_pct": 0,
            "reward_risk_ratio": 0,
            "total_pnl_pct": 0,
            "total_pnl_dollars": 0
          },
          "BY_ASSET": [],
          "BY_SOURCE": [],
          "BY_CONFIDENCE": [],
          "BY_EXIT_REASON": [],
          "BY_DIRECTION": [],
          "BY_ALIGNMENT": [],
          "BY_RSI_BAND": [],
          "BY_TREND": [],
          "BY_HOUR": [],
          "AVG_HOLD_TIME": {
            "avg_minutes": null,
            "avg_win_minutes": null,
            "avg_loss_minutes": null,
            "n": 0
          }
        },
        "closed": {
          "count": 0,
          "wins": 0,
          "losses": 0,
          "win_rate_pct": null,
          "total_pnl_dollars": 0,
          "low_sample": true
        }
      }
    }
  },
  "open_positions": [
    {
      "book_key": "news_only__hold_24hr",
      "portfolio": "news_only",
      "exit_rule": "hold_24hr",
      "asset": "AIFU",
      "direction": "LONG",
      "stake_amount": 1000,
      "shares": 400,
      "entry_price": 2.5,
      "current_price": 2.5,
      "unrealized_pnl_dollars": 0,
      "unrealized_pnl_percent": 0,
      "entry_time": "2026-06-11T13:40:45.993Z",
      "trade_id": "4f787d12-2e54-4202-9b6c-10c3acaa118d",
      "signal_id": "AIFU|BUY|AIFU signs MOU to acquire Peakleap Ventures",
      "title": "AIFU signs MOU to acquire Peakleap Ventures",
      "source": "Seeking Alpha RSS",
      "confidence": 0.65,
      "status": "OPEN",
      "row_id": "228",
      "asset_class": "stock",
      "current_price_at": "2026-06-11T15:25:31.144Z",
      "period_high": 2.58,
      "period_low": 2.5,
      "rule_version": "v2_20260609_stop2pct",
      "research_valid": true,
      "take_profit_pct": 0.04,
      "stop_loss_pct": 0.02,
      "take_profit_price": 2.6,
      "stop_loss_price": 2.45,
      "early_exit_threshold_pct": null,
      "effective_expiry_at": "2026-06-12T13:40:45.993Z"
    },
    {
      "book_key": "news_only__sell_eod",
      "portfolio": "news_only",
      "exit_rule": "sell_eod",
      "asset": "AIFU",
      "direction": "LONG",
      "stake_amount": 1000,
      "shares": 400,
      "entry_price": 2.5,
      "current_price": 2.5,
      "unrealized_pnl_dollars": 0,
      "unrealized_pnl_percent": 0,
      "entry_time": "2026-06-11T13:40:45.993Z",
      "trade_id": "4f787d12-2e54-4202-9b6c-10c3acaa118d",
      "signal_id": "AIFU|BUY|AIFU signs MOU to acquire Peakleap Ventures",
      "title": "AIFU signs MOU to acquire Peakleap Ventures",
      "source": "Seeking Alpha RSS",
      "confidence": 0.65,
      "status": "OPEN",
      "row_id": "229",
      "asset_class": "stock",
      "current_price_at": "2026-06-11T15:25:31.144Z",
      "period_high": 2.58,
      "period_low": 2.5,
      "rule_version": "v2_20260609_stop2pct",
      "research_valid": true,
      "take_profit_pct": 0.04,
      "stop_loss_pct": 0.02,
      "take_profit_price": 2.6,
      "stop_loss_price": 2.45,
      "early_exit_threshold_pct": 0.01,
      "effective_expiry_at": "2026-06-12T13:40:45.993Z"
    },
    {
      "book_key": "news_plus_ta__hold_24hr",
      "portfolio": "news_plus_ta",
      "exit_rule": "hold_24hr",
      "asset": "AIFU",
      "direction": "LONG",
      "stake_amount": 1000,
      "shares": 400,
      "entry_price": 2.5,
      "current_price": 2.5,
      "unrealized_pnl_dollars": 0,
      "unrealized_pnl_percent": 0,
      "entry_time": "2026-06-11T13:40:46.177Z",
      "trade_id": "4f787d12-2e54-4202-9b6c-10c3acaa118d",
      "signal_id": "AIFU|BUY|AIFU signs MOU to acquire Peakleap Ventures",
      "title": "AIFU signs MOU to acquire Peakleap Ventures",
      "source": "Seeking Alpha RSS",
      "confidence": 0.65,
      "status": "OPEN",
      "row_id": "232",
      "asset_class": "stock",
      "current_price_at": "2026-06-11T15:25:31.144Z",
      "period_high": 2.58,
      "period_low": 2.5,
      "rule_version": "v2_20260609_stop2pct",
      "research_valid": true,
      "take_profit_pct": 0.04,
      "stop_loss_pct": 0.02,
      "take_profit_price": 2.6,
      "stop_loss_price": 2.45,
      "early_exit_threshold_pct": null,
      "effective_expiry_at": "2026-06-12T13:40:46.177Z"
    },
    {
      "book_key": "news_only__sell_eod",
      "portfolio": "news_only",
      "exit_rule": "sell_eod",
      "asset": "CDNS",
      "direction": "LONG",
      "stake_amount": 900,
      "shares": 2.319289,
      "entry_price": 388.05,
      "current_price": 384.54,
      "unrealized_pnl_dollars": -8.14,
      "unrealized_pnl_percent": -0.009045,
      "entry_time": "2026-06-11T13:51:22.395Z",
      "trade_id": "dffcbc23-8866-44dd-abf3-be19e033e7bb",
      "signal_id": "CDNS|BUY|Cadence (CDNS) Expands Deal With Intel Foundry To Benefit From Agentic AI Boom",
      "title": "Cadence (CDNS) Expands Deal With Intel Foundry To Benefit From Agentic AI Boom",
      "source": "Yahoo Finance RSS",
      "confidence": 0.72,
      "status": "OPEN",
      "row_id": "239",
      "asset_class": "stock",
      "current_price_at": "2026-06-11T15:25:31.144Z",
      "period_high": 388.115,
      "period_low": 381.805,
      "rule_version": "v2_20260609_stop2pct",
      "research_valid": true,
      "take_profit_pct": 0.04,
      "stop_loss_pct": 0.02,
      "take_profit_price": 403.572,
      "stop_loss_price": 380.289,
      "early_exit_threshold_pct": 0.01,
      "effective_expiry_at": "2026-06-12T13:51:22.395Z"
    },
    {
      "book_key": "news_plus_ta__hold_24hr",
      "portfolio": "news_plus_ta",
      "exit_rule": "hold_24hr",
      "asset": "CDNS",
      "direction": "LONG",
      "stake_amount": 900,
      "shares": 2.319289,
      "entry_price": 388.05,
      "current_price": 384.54,
      "unrealized_pnl_dollars": -8.14,
      "unrealized_pnl_percent": -0.009045,
      "entry_time": "2026-06-11T13:51:22.591Z",
      "trade_id": "dffcbc23-8866-44dd-abf3-be19e033e7bb",
      "signal_id": "CDNS|BUY|Cadence (CDNS) Expands Deal With Intel Foundry To Benefit From Agentic AI Boom",
      "title": "Cadence (CDNS) Expands Deal With Intel Foundry To Benefit From Agentic AI Boom",
      "source": "Yahoo Finance RSS",
      "confidence": 0.72,
      "status": "OPEN",
      "row_id": "242",
      "asset_class": "stock",
      "current_price_at": "2026-06-11T15:25:31.144Z",
      "period_high": 388.115,
      "period_low": 381.805,
      "rule_version": "v2_20260609_stop2pct",
      "research_valid": true,
      "take_profit_pct": 0.04,
      "stop_loss_pct": 0.02,
      "take_profit_price": 403.572,
      "stop_loss_price": 380.289,
      "early_exit_threshold_pct": null,
      "effective_expiry_at": "2026-06-12T13:51:22.591Z"
    },
    {
      "book_key": "news_plus_ta__sell_eod",
      "portfolio": "news_plus_ta",
      "exit_rule": "sell_eod",
      "asset": "CDNS",
      "direction": "LONG",
      "stake_amount": 900,
      "shares": 2.319289,
      "entry_price": 388.05,
      "current_price": 384.54,
      "unrealized_pnl_dollars": -8.14,
      "unrealized_pnl_percent": -0.009045,
      "entry_time": "2026-06-11T13:51:22.591Z",
      "trade_id": "dffcbc23-8866-44dd-abf3-be19e033e7bb",
      "signal_id": "CDNS|BUY|Cadence (CDNS) Expands Deal With Intel Foundry To Benefit From Agentic AI Boom",
      "title": "Cadence (CDNS) Expands Deal With Intel Foundry To Benefit From Agentic AI Boom",
      "source": "Yahoo Finance RSS",
      "confidence": 0.72,
      "status": "OPEN",
      "row_id": "243",
      "asset_class": "stock",
      "current_price_at": "2026-06-11T15:25:31.144Z",
      "period_high": 388.115,
      "period_low": 381.805,
      "rule_version": "v2_20260609_stop2pct",
      "research_valid": true,
      "take_profit_pct": 0.04,
      "stop_loss_pct": 0.02,
      "take_profit_price": 403.572,
      "stop_loss_price": 380.289,
      "early_exit_threshold_pct": 0.01,
      "effective_expiry_at": "2026-06-12T13:51:22.591Z"
    },
    {
      "book_key": "mean_reversion__hold_24hr",
      "portfolio": "mean_reversion",
      "exit_rule": "hold_24hr",
      "asset": "AIFU",
      "direction": "LONG",
      "stake_amount": 1000,
      "shares": 400,
      "entry_price": 2.5,
      "current_price": 2.5,
      "unrealized_pnl_dollars": 0,
      "unrealized_pnl_percent": 0,
      "entry_time": "2026-06-11T13:40:45.828Z",
      "trade_id": "4f787d12-2e54-4202-9b6c-10c3acaa118d",
      "signal_id": "AIFU|BUY|AIFU signs MOU to acquire Peakleap Ventures",
      "title": "AIFU signs MOU to acquire Peakleap Ventures",
      "source": "Seeking Alpha RSS",
      "confidence": 0.65,
      "status": "OPEN",
      "row_id": "224",
      "asset_class": "stock",
      "current_price_at": "2026-06-11T15:25:31.144Z",
      "period_high": 2.58,
      "period_low": 2.5,
      "rule_version": "v2_20260609_stop2pct",
      "research_valid": true,
      "take_profit_pct": 0.04,
      "stop_loss_pct": 0.02,
      "take_profit_price": 2.6,
      "stop_loss_price": 2.45,
      "early_exit_threshold_pct": null,
      "effective_expiry_at": "2026-06-12T13:40:45.828Z"
    },
    {
      "book_key": "mean_reversion__sell_eod",
      "portfolio": "mean_reversion",
      "exit_rule": "sell_eod",
      "asset": "AIFU",
      "direction": "LONG",
      "stake_amount": 1000,
      "shares": 400,
      "entry_price": 2.5,
      "current_price": 2.5,
      "unrealized_pnl_dollars": 0,
      "unrealized_pnl_percent": 0,
      "entry_time": "2026-06-11T13:40:45.828Z",
      "trade_id": "4f787d12-2e54-4202-9b6c-10c3acaa118d",
      "signal_id": "AIFU|BUY|AIFU signs MOU to acquire Peakleap Ventures",
      "title": "AIFU signs MOU to acquire Peakleap Ventures",
      "source": "Seeking Alpha RSS",
      "confidence": 0.65,
      "status": "OPEN",
      "row_id": "225",
      "asset_class": "stock",
      "current_price_at": "2026-06-11T15:25:31.144Z",
      "period_high": 2.58,
      "period_low": 2.5,
      "rule_version": "v2_20260609_stop2pct",
      "research_valid": true,
      "take_profit_pct": 0.04,
      "stop_loss_pct": 0.02,
      "take_profit_price": 2.6,
      "stop_loss_price": 2.45,
      "early_exit_threshold_pct": 0.01,
      "effective_expiry_at": "2026-06-12T13:40:45.828Z"
    },
    {
      "book_key": "news_only__hold_24hr",
      "portfolio": "news_only",
      "exit_rule": "hold_24hr",
      "asset": "CDNS",
      "direction": "LONG",
      "stake_amount": 900,
      "shares": 2.319289,
      "entry_price": 388.05,
      "current_price": 384.54,
      "unrealized_pnl_dollars": -8.14,
      "unrealized_pnl_percent": -0.009045,
      "entry_time": "2026-06-11T13:51:22.395Z",
      "trade_id": "dffcbc23-8866-44dd-abf3-be19e033e7bb",
      "signal_id": "CDNS|BUY|Cadence (CDNS) Expands Deal With Intel Foundry To Benefit From Agentic AI Boom",
      "title": "Cadence (CDNS) Expands Deal With Intel Foundry To Benefit From Agentic AI Boom",
      "source": "Yahoo Finance RSS",
      "confidence": 0.72,
      "status": "OPEN",
      "row_id": "238",
      "asset_class": "stock",
      "current_price_at": "2026-06-11T15:25:31.144Z",
      "period_high": 388.115,
      "period_low": 381.805,
      "rule_version": "v2_20260609_stop2pct",
      "research_valid": true,
      "take_profit_pct": 0.04,
      "stop_loss_pct": 0.02,
      "take_profit_price": 403.572,
      "stop_loss_price": 380.289,
      "early_exit_threshold_pct": null,
      "effective_expiry_at": "2026-06-12T13:51:22.395Z"
    },
    {
      "book_key": "news_only__hold_24hr",
      "portfolio": "news_only",
      "exit_rule": "hold_24hr",
      "asset": "TROX",
      "direction": "LONG",
      "stake_amount": 729,
      "shares": 95.169713,
      "entry_price": 7.66,
      "current_price": 7.59,
      "unrealized_pnl_dollars": -6.66,
      "unrealized_pnl_percent": -0.009138,
      "entry_time": "2026-06-11T14:10:57.326Z",
      "trade_id": "9bd2ce78-d891-4926-91b4-d79e5f416797",
      "signal_id": "TROX|BUY|Tronox upgraded at Truist as improving materials pricing offsets some risks",
      "title": "Tronox upgraded at Truist as improving materials pricing offsets some risks",
      "source": "Seeking Alpha RSS",
      "confidence": 0.65,
      "status": "OPEN",
      "row_id": "250",
      "asset_class": "stock",
      "current_price_at": "2026-06-11T15:25:31.144Z",
      "period_high": 7.66,
      "period_low": 7.56,
      "rule_version": "v2_20260609_stop2pct",
      "research_valid": true,
      "take_profit_pct": 0.04,
      "stop_loss_pct": 0.02,
      "take_profit_price": 7.9664,
      "stop_loss_price": 7.5068,
      "early_exit_threshold_pct": null,
      "effective_expiry_at": "2026-06-12T14:10:57.326Z"
    },
    {
      "book_key": "news_only__sell_eod",
      "portfolio": "news_only",
      "exit_rule": "sell_eod",
      "asset": "TROX",
      "direction": "LONG",
      "stake_amount": 729,
      "shares": 95.169713,
      "entry_price": 7.66,
      "current_price": 7.59,
      "unrealized_pnl_dollars": -6.66,
      "unrealized_pnl_percent": -0.009138,
      "entry_time": "2026-06-11T14:10:57.326Z",
      "trade_id": "9bd2ce78-d891-4926-91b4-d79e5f416797",
      "signal_id": "TROX|BUY|Tronox upgraded at Truist as improving materials pricing offsets some risks",
      "title": "Tronox upgraded at Truist as improving materials pricing offsets some risks",
      "source": "Seeking Alpha RSS",
      "confidence": 0.65,
      "status": "OPEN",
      "row_id": "251",
      "asset_class": "stock",
      "current_price_at": "2026-06-11T15:25:31.144Z",
      "period_high": 7.66,
      "period_low": 7.56,
      "rule_version": "v2_20260609_stop2pct",
      "research_valid": true,
      "take_profit_pct": 0.04,
      "stop_loss_pct": 0.02,
      "take_profit_price": 7.9664,
      "stop_loss_price": 7.5068,
      "early_exit_threshold_pct": 0.01,
      "effective_expiry_at": "2026-06-12T14:10:57.326Z"
    },
    {
      "book_key": "news_plus_ta__sell_eod",
      "portfolio": "news_plus_ta",
      "exit_rule": "sell_eod",
      "asset": "AIFU",
      "direction": "LONG",
      "stake_amount": 1000,
      "shares": 400,
      "entry_price": 2.5,
      "current_price": 2.5,
      "unrealized_pnl_dollars": 0,
      "unrealized_pnl_percent": 0,
      "entry_time": "2026-06-11T13:40:46.177Z",
      "trade_id": "4f787d12-2e54-4202-9b6c-10c3acaa118d",
      "signal_id": "AIFU|BUY|AIFU signs MOU to acquire Peakleap Ventures",
      "title": "AIFU signs MOU to acquire Peakleap Ventures",
      "source": "Seeking Alpha RSS",
      "confidence": 0.65,
      "status": "OPEN",
      "row_id": "233",
      "asset_class": "stock",
      "current_price_at": "2026-06-11T15:25:31.144Z",
      "period_high": 2.58,
      "period_low": 2.5,
      "rule_version": "v2_20260609_stop2pct",
      "research_valid": true,
      "take_profit_pct": 0.04,
      "stop_loss_pct": 0.02,
      "take_profit_price": 2.6,
      "stop_loss_price": 2.45,
      "early_exit_threshold_pct": 0.01,
      "effective_expiry_at": "2026-06-12T13:40:46.177Z"
    },
    {
      "book_key": "trend_strict__hold_24hr",
      "portfolio": "trend_strict",
      "exit_rule": "hold_24hr",
      "asset": "AIFU",
      "direction": "LONG",
      "stake_amount": 1000,
      "shares": 400,
      "entry_price": 2.5,
      "current_price": 2.5,
      "unrealized_pnl_dollars": 0,
      "unrealized_pnl_percent": 0,
      "entry_time": "2026-06-11T13:40:46.325Z",
      "trade_id": "4f787d12-2e54-4202-9b6c-10c3acaa118d",
      "signal_id": "AIFU|BUY|AIFU signs MOU to acquire Peakleap Ventures",
      "title": "AIFU signs MOU to acquire Peakleap Ventures",
      "source": "Seeking Alpha RSS",
      "confidence": 0.65,
      "status": "OPEN",
      "row_id": "236",
      "asset_class": "stock",
      "current_price_at": "2026-06-11T15:25:31.144Z",
      "period_high": 2.58,
      "period_low": 2.5,
      "rule_version": "v2_20260609_stop2pct",
      "research_valid": true,
      "take_profit_pct": 0.04,
      "stop_loss_pct": 0.02,
      "take_profit_price": 2.6,
      "stop_loss_price": 2.45,
      "early_exit_threshold_pct": null,
      "effective_expiry_at": "2026-06-12T13:40:46.325Z"
    },
    {
      "book_key": "trend_strict__sell_eod",
      "portfolio": "trend_strict",
      "exit_rule": "sell_eod",
      "asset": "AIFU",
      "direction": "LONG",
      "stake_amount": 1000,
      "shares": 400,
      "entry_price": 2.5,
      "current_price": 2.5,
      "unrealized_pnl_dollars": 0,
      "unrealized_pnl_percent": 0,
      "entry_time": "2026-06-11T13:40:46.325Z",
      "trade_id": "4f787d12-2e54-4202-9b6c-10c3acaa118d",
      "signal_id": "AIFU|BUY|AIFU signs MOU to acquire Peakleap Ventures",
      "title": "AIFU signs MOU to acquire Peakleap Ventures",
      "source": "Seeking Alpha RSS",
      "confidence": 0.65,
      "status": "OPEN",
      "row_id": "237",
      "asset_class": "stock",
      "current_price_at": "2026-06-11T15:25:31.144Z",
      "period_high": 2.58,
      "period_low": 2.5,
      "rule_version": "v2_20260609_stop2pct",
      "research_valid": true,
      "take_profit_pct": 0.04,
      "stop_loss_pct": 0.02,
      "take_profit_price": 2.6,
      "stop_loss_price": 2.45,
      "early_exit_threshold_pct": 0.01,
      "effective_expiry_at": "2026-06-12T13:40:46.325Z"
    },
    {
      "book_key": "news_only__hold_24hr",
      "portfolio": "news_only",
      "exit_rule": "hold_24hr",
      "asset": "ASYS",
      "direction": "LONG",
      "stake_amount": 810,
      "shares": 40.212481,
      "entry_price": 20.143,
      "current_price": 20.177,
      "unrealized_pnl_dollars": 1.37,
      "unrealized_pnl_percent": 0.001688,
      "entry_time": "2026-06-11T14:10:57.326Z",
      "trade_id": "4dbe9ec3-0df6-48c0-a63c-7403deb82a3f",
      "signal_id": "ASYS|BUY|Amtech Systems set to join Russell 3000, Russell 2000 indexes",
      "title": "Amtech Systems set to join Russell 3000, Russell 2000 indexes",
      "source": "Seeking Alpha RSS",
      "confidence": 0.65,
      "status": "OPEN",
      "row_id": "246",
      "asset_class": "stock",
      "current_price_at": "2026-06-11T15:25:31.144Z",
      "period_high": 20.255,
      "period_low": 20.01,
      "rule_version": "v2_20260609_stop2pct",
      "research_valid": true,
      "take_profit_pct": 0.04,
      "stop_loss_pct": 0.02,
      "take_profit_price": 20.94872,
      "stop_loss_price": 19.74014,
      "early_exit_threshold_pct": null,
      "effective_expiry_at": "2026-06-12T14:10:57.326Z"
    },
    {
      "book_key": "news_only__sell_eod",
      "portfolio": "news_only",
      "exit_rule": "sell_eod",
      "asset": "ASYS",
      "direction": "LONG",
      "stake_amount": 810,
      "shares": 40.212481,
      "entry_price": 20.143,
      "current_price": 20.177,
      "unrealized_pnl_dollars": 1.37,
      "unrealized_pnl_percent": 0.001688,
      "entry_time": "2026-06-11T14:10:57.326Z",
      "trade_id": "4dbe9ec3-0df6-48c0-a63c-7403deb82a3f",
      "signal_id": "ASYS|BUY|Amtech Systems set to join Russell 3000, Russell 2000 indexes",
      "title": "Amtech Systems set to join Russell 3000, Russell 2000 indexes",
      "source": "Seeking Alpha RSS",
      "confidence": 0.65,
      "status": "OPEN",
      "row_id": "247",
      "asset_class": "stock",
      "current_price_at": "2026-06-11T15:25:31.144Z",
      "period_high": 20.255,
      "period_low": 20.01,
      "rule_version": "v2_20260609_stop2pct",
      "research_valid": true,
      "take_profit_pct": 0.04,
      "stop_loss_pct": 0.02,
      "take_profit_price": 20.94872,
      "stop_loss_price": 19.74014,
      "early_exit_threshold_pct": 0.01,
      "effective_expiry_at": "2026-06-12T14:10:57.326Z"
    },
    {
      "book_key": "news_only__hold_24hr",
      "portfolio": "news_only",
      "exit_rule": "hold_24hr",
      "asset": "GME",
      "direction": "LONG",
      "stake_amount": 656.1,
      "shares": 29.634146,
      "entry_price": 22.14,
      "current_price": 22.18,
      "unrealized_pnl_dollars": 1.19,
      "unrealized_pnl_percent": 0.001807,
      "entry_time": "2026-06-11T14:50:28.862Z",
      "trade_id": "5142a66d-fa77-47d5-acce-6e545432cdda",
      "signal_id": "GME|BUY|GameStop Surges on Q1 Beat, $2B Buyback, $39 Target",
      "title": "GameStop Surges on Q1 Beat, $2B Buyback, $39 Target",
      "source": "Yahoo Finance RSS",
      "confidence": 0.72,
      "status": "OPEN",
      "row_id": "254",
      "asset_class": "stock",
      "current_price_at": "2026-06-11T15:25:31.144Z",
      "period_high": 22.18,
      "period_low": 22.065,
      "rule_version": "v2_20260609_stop2pct",
      "research_valid": true,
      "take_profit_pct": 0.04,
      "stop_loss_pct": 0.02,
      "take_profit_price": 23.0256,
      "stop_loss_price": 21.6972,
      "early_exit_threshold_pct": null,
      "effective_expiry_at": "2026-06-12T14:50:28.862Z"
    },
    {
      "book_key": "news_only__sell_eod",
      "portfolio": "news_only",
      "exit_rule": "sell_eod",
      "asset": "GME",
      "direction": "LONG",
      "stake_amount": 656.1,
      "shares": 29.634146,
      "entry_price": 22.14,
      "current_price": 22.18,
      "unrealized_pnl_dollars": 1.19,
      "unrealized_pnl_percent": 0.001807,
      "entry_time": "2026-06-11T14:50:28.862Z",
      "trade_id": "5142a66d-fa77-47d5-acce-6e545432cdda",
      "signal_id": "GME|BUY|GameStop Surges on Q1 Beat, $2B Buyback, $39 Target",
      "title": "GameStop Surges on Q1 Beat, $2B Buyback, $39 Target",
      "source": "Yahoo Finance RSS",
      "confidence": 0.72,
      "status": "OPEN",
      "row_id": "255",
      "asset_class": "stock",
      "current_price_at": "2026-06-11T15:25:31.144Z",
      "period_high": 22.18,
      "period_low": 22.058,
      "rule_version": "v2_20260609_stop2pct",
      "research_valid": true,
      "take_profit_pct": 0.04,
      "stop_loss_pct": 0.02,
      "take_profit_price": 23.0256,
      "stop_loss_price": 21.6972,
      "early_exit_threshold_pct": 0.01,
      "effective_expiry_at": "2026-06-12T14:50:28.862Z"
    },
    {
      "book_key": "news_plus_ta__hold_24hr",
      "portfolio": "news_plus_ta",
      "exit_rule": "hold_24hr",
      "asset": "IDCC",
      "direction": "LONG",
      "stake_amount": 729,
      "shares": 2.641209,
      "entry_price": 276.01,
      "current_price": 279.88,
      "unrealized_pnl_dollars": 10.22,
      "unrealized_pnl_percent": 0.014021,
      "entry_time": "2026-06-11T15:00:27.983Z",
      "trade_id": "9f41bfcd-fb2e-4ead-b331-af4f7a5a92bf",
      "signal_id": "IDCC|BUY|InterDigital Signs Amazon License Agreement Covering Video Services and Devices, Expands Streaming Royalty Opportunity (IDCC)",
      "title": "InterDigital Signs Amazon License Agreement Covering Video Services and Devices, Expands Streaming Royalty Opportunity (IDCC)",
      "source": "Yahoo Finance RSS",
      "confidence": 0.72,
      "status": "OPEN",
      "row_id": "270",
      "asset_class": "stock",
      "current_price_at": "2026-06-11T15:25:31.144Z",
      "period_high": 279.88,
      "period_low": 276.01,
      "rule_version": "v2_20260609_stop2pct",
      "research_valid": true,
      "take_profit_pct": 0.04,
      "stop_loss_pct": 0.02,
      "take_profit_price": 287.0504,
      "stop_loss_price": 270.4898,
      "early_exit_threshold_pct": null,
      "effective_expiry_at": "2026-06-12T15:00:27.983Z"
    },
    {
      "book_key": "news_plus_ta__hold_24hr",
      "portfolio": "news_plus_ta",
      "exit_rule": "hold_24hr",
      "asset": "GME",
      "direction": "LONG",
      "stake_amount": 810,
      "shares": 36.585366,
      "entry_price": 22.14,
      "current_price": 22.18,
      "unrealized_pnl_dollars": 1.46,
      "unrealized_pnl_percent": 0.001807,
      "entry_time": "2026-06-11T14:50:29.074Z",
      "trade_id": "5142a66d-fa77-47d5-acce-6e545432cdda",
      "signal_id": "GME|BUY|GameStop Surges on Q1 Beat, $2B Buyback, $39 Target",
      "title": "GameStop Surges on Q1 Beat, $2B Buyback, $39 Target",
      "source": "Yahoo Finance RSS",
      "confidence": 0.72,
      "status": "OPEN",
      "row_id": "258",
      "asset_class": "stock",
      "current_price_at": "2026-06-11T15:25:31.144Z",
      "period_high": 22.18,
      "period_low": 22.058,
      "rule_version": "v2_20260609_stop2pct",
      "research_valid": true,
      "take_profit_pct": 0.04,
      "stop_loss_pct": 0.02,
      "take_profit_price": 23.0256,
      "stop_loss_price": 21.6972,
      "early_exit_threshold_pct": null,
      "effective_expiry_at": "2026-06-12T14:50:29.074Z"
    },
    {
      "book_key": "mean_reversion__hold_24hr",
      "portfolio": "mean_reversion",
      "exit_rule": "hold_24hr",
      "asset": "IDCC",
      "direction": "LONG",
      "stake_amount": 900,
      "shares": 3.260751,
      "entry_price": 276.01,
      "current_price": 279.88,
      "unrealized_pnl_dollars": 12.62,
      "unrealized_pnl_percent": 0.014021,
      "entry_time": "2026-06-11T15:00:27.619Z",
      "trade_id": "9f41bfcd-fb2e-4ead-b331-af4f7a5a92bf",
      "signal_id": "IDCC|BUY|InterDigital Signs Amazon License Agreement Covering Video Services and Devices, Expands Streaming Royalty Opportunity (IDCC)",
      "title": "InterDigital Signs Amazon License Agreement Covering Video Services and Devices, Expands Streaming Royalty Opportunity (IDCC)",
      "source": "Yahoo Finance RSS",
      "confidence": 0.72,
      "status": "OPEN",
      "row_id": "262",
      "asset_class": "stock",
      "current_price_at": "2026-06-11T15:25:31.144Z",
      "period_high": 279.88,
      "period_low": 276.01,
      "rule_version": "v2_20260609_stop2pct",
      "research_valid": true,
      "take_profit_pct": 0.04,
      "stop_loss_pct": 0.02,
      "take_profit_price": 287.0504,
      "stop_loss_price": 270.4898,
      "early_exit_threshold_pct": null,
      "effective_expiry_at": "2026-06-12T15:00:27.619Z"
    },
    {
      "book_key": "mean_reversion__sell_eod",
      "portfolio": "mean_reversion",
      "exit_rule": "sell_eod",
      "asset": "IDCC",
      "direction": "LONG",
      "stake_amount": 900,
      "shares": 3.260751,
      "entry_price": 276.01,
      "current_price": 279.88,
      "unrealized_pnl_dollars": 12.62,
      "unrealized_pnl_percent": 0.014021,
      "entry_time": "2026-06-11T15:00:27.619Z",
      "trade_id": "9f41bfcd-fb2e-4ead-b331-af4f7a5a92bf",
      "signal_id": "IDCC|BUY|InterDigital Signs Amazon License Agreement Covering Video Services and Devices, Expands Streaming Royalty Opportunity (IDCC)",
      "title": "InterDigital Signs Amazon License Agreement Covering Video Services and Devices, Expands Streaming Royalty Opportunity (IDCC)",
      "source": "Yahoo Finance RSS",
      "confidence": 0.72,
      "status": "OPEN",
      "row_id": "263",
      "asset_class": "stock",
      "current_price_at": "2026-06-11T15:25:31.144Z",
      "period_high": 279.88,
      "period_low": 276.01,
      "rule_version": "v2_20260609_stop2pct",
      "research_valid": true,
      "take_profit_pct": 0.04,
      "stop_loss_pct": 0.02,
      "take_profit_price": 287.0504,
      "stop_loss_price": 270.4898,
      "early_exit_threshold_pct": 0.01,
      "effective_expiry_at": "2026-06-12T15:00:27.619Z"
    },
    {
      "book_key": "news_only__hold_24hr",
      "portfolio": "news_only",
      "exit_rule": "hold_24hr",
      "asset": "IDCC",
      "direction": "LONG",
      "stake_amount": 590.49,
      "shares": 2.139379,
      "entry_price": 276.01,
      "current_price": 279.88,
      "unrealized_pnl_dollars": 8.28,
      "unrealized_pnl_percent": 0.014021,
      "entry_time": "2026-06-11T15:00:27.790Z",
      "trade_id": "9f41bfcd-fb2e-4ead-b331-af4f7a5a92bf",
      "signal_id": "IDCC|BUY|InterDigital Signs Amazon License Agreement Covering Video Services and Devices, Expands Streaming Royalty Opportunity (IDCC)",
      "title": "InterDigital Signs Amazon License Agreement Covering Video Services and Devices, Expands Streaming Royalty Opportunity (IDCC)",
      "source": "Yahoo Finance RSS",
      "confidence": 0.72,
      "status": "OPEN",
      "row_id": "266",
      "asset_class": "stock",
      "current_price_at": "2026-06-11T15:25:31.144Z",
      "period_high": 279.88,
      "period_low": 276.01,
      "rule_version": "v2_20260609_stop2pct",
      "research_valid": true,
      "take_profit_pct": 0.04,
      "stop_loss_pct": 0.02,
      "take_profit_price": 287.0504,
      "stop_loss_price": 270.4898,
      "early_exit_threshold_pct": null,
      "effective_expiry_at": "2026-06-12T15:00:27.790Z"
    },
    {
      "book_key": "news_only__sell_eod",
      "portfolio": "news_only",
      "exit_rule": "sell_eod",
      "asset": "IDCC",
      "direction": "LONG",
      "stake_amount": 590.49,
      "shares": 2.139379,
      "entry_price": 276.01,
      "current_price": 279.88,
      "unrealized_pnl_dollars": 8.28,
      "unrealized_pnl_percent": 0.014021,
      "entry_time": "2026-06-11T15:00:27.790Z",
      "trade_id": "9f41bfcd-fb2e-4ead-b331-af4f7a5a92bf",
      "signal_id": "IDCC|BUY|InterDigital Signs Amazon License Agreement Covering Video Services and Devices, Expands Streaming Royalty Opportunity (IDCC)",
      "title": "InterDigital Signs Amazon License Agreement Covering Video Services and Devices, Expands Streaming Royalty Opportunity (IDCC)",
      "source": "Yahoo Finance RSS",
      "confidence": 0.72,
      "status": "OPEN",
      "row_id": "267",
      "asset_class": "stock",
      "current_price_at": "2026-06-11T15:25:31.144Z",
      "period_high": 279.88,
      "period_low": 276.01,
      "rule_version": "v2_20260609_stop2pct",
      "research_valid": true,
      "take_profit_pct": 0.04,
      "stop_loss_pct": 0.02,
      "take_profit_price": 287.0504,
      "stop_loss_price": 270.4898,
      "early_exit_threshold_pct": 0.01,
      "effective_expiry_at": "2026-06-12T15:00:27.790Z"
    },
    {
      "book_key": "news_plus_ta__sell_eod",
      "portfolio": "news_plus_ta",
      "exit_rule": "sell_eod",
      "asset": "IDCC",
      "direction": "LONG",
      "stake_amount": 729,
      "shares": 2.641209,
      "entry_price": 276.01,
      "current_price": 279.88,
      "unrealized_pnl_dollars": 10.22,
      "unrealized_pnl_percent": 0.014021,
      "entry_time": "2026-06-11T15:00:27.983Z",
      "trade_id": "9f41bfcd-fb2e-4ead-b331-af4f7a5a92bf",
      "signal_id": "IDCC|BUY|InterDigital Signs Amazon License Agreement Covering Video Services and Devices, Expands Streaming Royalty Opportunity (IDCC)",
      "title": "InterDigital Signs Amazon License Agreement Covering Video Services and Devices, Expands Streaming Royalty Opportunity (IDCC)",
      "source": "Yahoo Finance RSS",
      "confidence": 0.72,
      "status": "OPEN",
      "row_id": "271",
      "asset_class": "stock",
      "current_price_at": "2026-06-11T15:25:31.144Z",
      "period_high": 279.88,
      "period_low": 276.01,
      "rule_version": "v2_20260609_stop2pct",
      "research_valid": true,
      "take_profit_pct": 0.04,
      "stop_loss_pct": 0.02,
      "take_profit_price": 287.0504,
      "stop_loss_price": 270.4898,
      "early_exit_threshold_pct": 0.01,
      "effective_expiry_at": "2026-06-12T15:00:27.983Z"
    },
    {
      "book_key": "trend_strict__hold_24hr",
      "portfolio": "trend_strict",
      "exit_rule": "hold_24hr",
      "asset": "IDCC",
      "direction": "LONG",
      "stake_amount": 900,
      "shares": 3.260751,
      "entry_price": 276.01,
      "current_price": 279.88,
      "unrealized_pnl_dollars": 12.62,
      "unrealized_pnl_percent": 0.014021,
      "entry_time": "2026-06-11T15:00:28.129Z",
      "trade_id": "9f41bfcd-fb2e-4ead-b331-af4f7a5a92bf",
      "signal_id": "IDCC|BUY|InterDigital Signs Amazon License Agreement Covering Video Services and Devices, Expands Streaming Royalty Opportunity (IDCC)",
      "title": "InterDigital Signs Amazon License Agreement Covering Video Services and Devices, Expands Streaming Royalty Opportunity (IDCC)",
      "source": "Yahoo Finance RSS",
      "confidence": 0.72,
      "status": "OPEN",
      "row_id": "274",
      "asset_class": "stock",
      "current_price_at": "2026-06-11T15:25:31.144Z",
      "period_high": 279.88,
      "period_low": 276.01,
      "rule_version": "v2_20260609_stop2pct",
      "research_valid": true,
      "take_profit_pct": 0.04,
      "stop_loss_pct": 0.02,
      "take_profit_price": 287.0504,
      "stop_loss_price": 270.4898,
      "early_exit_threshold_pct": null,
      "effective_expiry_at": "2026-06-12T15:00:28.129Z"
    },
    {
      "book_key": "trend_strict__sell_eod",
      "portfolio": "trend_strict",
      "exit_rule": "sell_eod",
      "asset": "IDCC",
      "direction": "LONG",
      "stake_amount": 900,
      "shares": 3.260751,
      "entry_price": 276.01,
      "current_price": 279.88,
      "unrealized_pnl_dollars": 12.62,
      "unrealized_pnl_percent": 0.014021,
      "entry_time": "2026-06-11T15:00:28.129Z",
      "trade_id": "9f41bfcd-fb2e-4ead-b331-af4f7a5a92bf",
      "signal_id": "IDCC|BUY|InterDigital Signs Amazon License Agreement Covering Video Services and Devices, Expands Streaming Royalty Opportunity (IDCC)",
      "title": "InterDigital Signs Amazon License Agreement Covering Video Services and Devices, Expands Streaming Royalty Opportunity (IDCC)",
      "source": "Yahoo Finance RSS",
      "confidence": 0.72,
      "status": "OPEN",
      "row_id": "275",
      "asset_class": "stock",
      "current_price_at": "2026-06-11T15:25:31.144Z",
      "period_high": 279.88,
      "period_low": 276.01,
      "rule_version": "v2_20260609_stop2pct",
      "research_valid": true,
      "take_profit_pct": 0.04,
      "stop_loss_pct": 0.02,
      "take_profit_price": 287.0504,
      "stop_loss_price": 270.4898,
      "early_exit_threshold_pct": 0.01,
      "effective_expiry_at": "2026-06-12T15:00:28.129Z"
    },
    {
      "book_key": "news_plus_ta__sell_eod",
      "portfolio": "news_plus_ta",
      "exit_rule": "sell_eod",
      "asset": "GME",
      "direction": "LONG",
      "stake_amount": 810,
      "shares": 36.585366,
      "entry_price": 22.14,
      "current_price": 22.18,
      "unrealized_pnl_dollars": 1.46,
      "unrealized_pnl_percent": 0.001807,
      "entry_time": "2026-06-11T14:50:29.074Z",
      "trade_id": "5142a66d-fa77-47d5-acce-6e545432cdda",
      "signal_id": "GME|BUY|GameStop Surges on Q1 Beat, $2B Buyback, $39 Target",
      "title": "GameStop Surges on Q1 Beat, $2B Buyback, $39 Target",
      "source": "Yahoo Finance RSS",
      "confidence": 0.72,
      "status": "OPEN",
      "row_id": "259",
      "asset_class": "stock",
      "current_price_at": "2026-06-11T15:25:31.144Z",
      "period_high": 22.18,
      "period_low": 22.058,
      "rule_version": "v2_20260609_stop2pct",
      "research_valid": true,
      "take_profit_pct": 0.04,
      "stop_loss_pct": 0.02,
      "take_profit_price": 23.0256,
      "stop_loss_price": 21.6972,
      "early_exit_threshold_pct": 0.01,
      "effective_expiry_at": "2026-06-12T14:50:29.074Z"
    },
    {
      "book_key": "news_only__hold_24hr",
      "portfolio": "news_only",
      "exit_rule": "hold_24hr",
      "asset": "CCJ",
      "direction": "LONG",
      "stake_amount": 531.44,
      "shares": 5.493772,
      "entry_price": 96.735,
      "current_price": 96.735,
      "unrealized_pnl_dollars": 0,
      "unrealized_pnl_percent": 0,
      "entry_time": "2026-06-11T15:30:40.936Z",
      "trade_id": "d97ec86c-8f4d-48b6-9064-186cd8678b4e",
      "signal_id": "CCJ|BUY|Cameco (CCJ), Orano to Acquire TEPCO Resources' Stake in Cigar Lake JV",
      "title": "Cameco (CCJ), Orano to Acquire TEPCO Resources' Stake in Cigar Lake JV",
      "source": "Yahoo Finance RSS",
      "confidence": 0.72,
      "status": "OPEN",
      "row_id": "276",
      "asset_class": "stock",
      "current_price_at": "2026-06-11T15:30:40.936Z",
      "period_high": 96.735,
      "period_low": 96.735,
      "rule_version": "v2_20260609_stop2pct",
      "research_valid": true,
      "take_profit_pct": 0.04,
      "stop_loss_pct": 0.02,
      "take_profit_price": 100.6044,
      "stop_loss_price": 94.8003,
      "early_exit_threshold_pct": null,
      "effective_expiry_at": "2026-06-12T15:30:40.936Z"
    },
    {
      "book_key": "news_only__sell_eod",
      "portfolio": "news_only",
      "exit_rule": "sell_eod",
      "asset": "CCJ",
      "direction": "LONG",
      "stake_amount": 531.44,
      "shares": 5.493772,
      "entry_price": 96.735,
      "current_price": 96.735,
      "unrealized_pnl_dollars": 0,
      "unrealized_pnl_percent": 0,
      "entry_time": "2026-06-11T15:30:40.936Z",
      "trade_id": "d97ec86c-8f4d-48b6-9064-186cd8678b4e",
      "signal_id": "CCJ|BUY|Cameco (CCJ), Orano to Acquire TEPCO Resources' Stake in Cigar Lake JV",
      "title": "Cameco (CCJ), Orano to Acquire TEPCO Resources' Stake in Cigar Lake JV",
      "source": "Yahoo Finance RSS",
      "confidence": 0.72,
      "status": "OPEN",
      "row_id": "277",
      "asset_class": "stock",
      "current_price_at": "2026-06-11T15:30:40.936Z",
      "period_high": 96.735,
      "period_low": 96.735,
      "rule_version": "v2_20260609_stop2pct",
      "research_valid": true,
      "take_profit_pct": 0.04,
      "stop_loss_pct": 0.02,
      "take_profit_price": 100.6044,
      "stop_loss_price": 94.8003,
      "early_exit_threshold_pct": 0.01,
      "effective_expiry_at": "2026-06-12T15:30:40.936Z"
    },
    {
      "book_key": "news_only__hold_24hr",
      "portfolio": "news_only",
      "exit_rule": "hold_24hr",
      "asset": "CLS",
      "direction": "LONG",
      "stake_amount": 478.3,
      "shares": 1.291603,
      "entry_price": 370.315,
      "current_price": 370.315,
      "unrealized_pnl_dollars": 0,
      "unrealized_pnl_percent": 0,
      "entry_time": "2026-06-11T15:30:40.936Z",
      "trade_id": "5ba49a07-a2e7-4875-88f3-4140e46ba3fa",
      "signal_id": "CLS|BUY|Celestica (CLS) to Establish New Manufacturing Campus in Fort Worth, Texas",
      "title": "Celestica (CLS) to Establish New Manufacturing Campus in Fort Worth, Texas",
      "source": "Yahoo Finance RSS",
      "confidence": 0.65,
      "status": "OPEN",
      "row_id": "280",
      "asset_class": "stock",
      "current_price_at": "2026-06-11T15:30:40.936Z",
      "period_high": 370.315,
      "period_low": 370.315,
      "rule_version": "v2_20260609_stop2pct",
      "research_valid": true,
      "take_profit_pct": 0.04,
      "stop_loss_pct": 0.02,
      "take_profit_price": 385.1276,
      "stop_loss_price": 362.9087,
      "early_exit_threshold_pct": null,
      "effective_expiry_at": "2026-06-12T15:30:40.936Z"
    },
    {
      "book_key": "news_only__sell_eod",
      "portfolio": "news_only",
      "exit_rule": "sell_eod",
      "asset": "CLS",
      "direction": "LONG",
      "stake_amount": 478.3,
      "shares": 1.291603,
      "entry_price": 370.315,
      "current_price": 370.315,
      "unrealized_pnl_dollars": 0,
      "unrealized_pnl_percent": 0,
      "entry_time": "2026-06-11T15:30:40.936Z",
      "trade_id": "5ba49a07-a2e7-4875-88f3-4140e46ba3fa",
      "signal_id": "CLS|BUY|Celestica (CLS) to Establish New Manufacturing Campus in Fort Worth, Texas",
      "title": "Celestica (CLS) to Establish New Manufacturing Campus in Fort Worth, Texas",
      "source": "Yahoo Finance RSS",
      "confidence": 0.65,
      "status": "OPEN",
      "row_id": "281",
      "asset_class": "stock",
      "current_price_at": "2026-06-11T15:30:40.936Z",
      "period_high": 370.315,
      "period_low": 370.315,
      "rule_version": "v2_20260609_stop2pct",
      "research_valid": true,
      "take_profit_pct": 0.04,
      "stop_loss_pct": 0.02,
      "take_profit_price": 385.1276,
      "stop_loss_price": 362.9087,
      "early_exit_threshold_pct": 0.01,
      "effective_expiry_at": "2026-06-12T15:30:40.936Z"
    }
  ],
  "closed_trades": [],
  "low_sample_threshold": 20
}